<?xml version="1.0" encoding="utf-8"?>
<Defs>
	<EnemyShipDef>
		<defName>FrigateAssault</defName>
		<saveSysVer>2</saveSysVer>
		<offsetX>92</offsetX>
		<offsetZ>100</offsetZ>
		<sizeX>61</sizeX>
		<sizeZ>50</sizeZ>
		<label>Assault frigate</label>
		<combatPoints>351</combatPoints>
		<core>
			<shapeOrDef>ShipConsoleTactical</shapeOrDef>
			<x>28</x>
			<z>23</z>
		</core>
		<symbolTable>
			<li>
				<key>?</key>
				<value>
					<shapeOrDef>ShipHullTile</shapeOrDef>
				</value>
			</li>
			<li>
				<key>@</key>
				<value>
					<shapeOrDef>Ship_Beam_Unpowered</shapeOrDef>
				</value>
			</li>
			<li>
				<key>A</key>
				<value>
					<shapeOrDef>Ship_Corner_OneOne</shapeOrDef>
				</value>
			</li>
			<li>
				<key>B</key>
				<value>
					<shapeOrDef>ShipAirlock</shapeOrDef>
				</value>
			</li>
			<li>
				<key>C</key>
				<value>
					<shapeOrDef>Ship_Corner_OneTwoFlip</shapeOrDef>
				</value>
			</li>
			<li>
				<key>D</key>
				<value>
					<shapeOrDef>Ship_Corner_OneTwo</shapeOrDef>
				</value>
			</li>
			<li>
				<key>E</key>
				<value>
					<shapeOrDef>ShipHeatsink</shapeOrDef>
				</value>
			</li>
			<li>
				<key>F</key>
				<value>
					<shapeOrDef>Ship_Corner_OneThree</shapeOrDef>
				</value>
			</li>
			<li>
				<key>G</key>
				<value>
					<shapeOrDef>Ship_Corner_OneThreeFlip</shapeOrDef>
				</value>
			</li>
			<li>
				<key>H</key>
				<value>
					<shapeOrDef>Ship_Engine</shapeOrDef>
				</value>
			</li>
			<li>
				<key>I</key>
				<value>
					<shapeOrDef>ShipSpinalAmplifier</shapeOrDef>
				</value>
			</li>
			<li>
				<key>J</key>
				<value>
					<shapeOrDef>ShipSpinalEmitter</shapeOrDef>
				</value>
			</li>
			<li>
				<key>K</key>
				<value>
					<shapeOrDef>ShipSpinalBarrelLaser</shapeOrDef>
				</value>
			</li>
			<li>
				<key>L</key>
				<value>
					<shapeOrDef>Ship_Beam</shapeOrDef>
				</value>
			</li>
			<li>
				<key>M</key>
				<value>
					<shapeOrDef>ShipCapacitorSmall</shapeOrDef>
				</value>
			</li>
			<li>
				<key>N</key>
				<value>
					<shapeOrDef>ShipCapacitor</shapeOrDef>
				</value>
			</li>
			<li>
				<key>O</key>
				<value>
					<shapeOrDef>ShipCombatShieldGenerator</shapeOrDef>
					<radius>45</radius>
				</value>
			</li>
			<li>
				<key>P</key>
				<value>
					<shapeOrDef>Ship_Corner_OneOneFlip</shapeOrDef>
				</value>
			</li>
			<li>
				<key>Q</key>
				<value>
					<shapeOrDef>ShipTurret_Laser</shapeOrDef>
				</value>
			</li>
			<li>
				<key>R</key>
				<value>
					<shapeOrDef>Ship_CryptosleepCasket</shapeOrDef>
				</value>
			</li>
			<li>
				<key>S</key>
				<value>
					<shapeOrDef>Bed</shapeOrDef>
					<stuff>Steel</stuff>
				</value>
			</li>
			<li>
				<key>T</key>
				<value>
					<shapeOrDef>HospitalBed</shapeOrDef>
					<stuff>Steel</stuff>
				</value>
			</li>
			<li>
				<key>U</key>
				<value>
					<shapeOrDef>VitalsMonitor</shapeOrDef>
				</value>
			</li>
			<li>
				<key>V</key>
				<value>
					<shapeOrDef>Shelf</shapeOrDef>
					<stuff>Steel</stuff>
				</value>
			</li>
			<li>
				<key>W</key>
				<value>
					<shapeOrDef>Dresser</shapeOrDef>
					<stuff>Steel</stuff>
				</value>
			</li>
			<li>
				<key>X</key>
				<value>
					<shapeOrDef>EndTable</shapeOrDef>
					<stuff>Steel</stuff>
				</value>
			</li>
			<li>
				<key>Y</key>
				<value>
					<shapeOrDef>Ship_Reactor</shapeOrDef>
				</value>
			</li>
			<li>
				<key>Z</key>
				<value>
					<shapeOrDef>ShipHeatsinkLarge</shapeOrDef>
				</value>
			</li>
			<li>
				<key>[</key>
				<value>
					<shapeOrDef>Ship_ComputerCore</shapeOrDef>
				</value>
			</li>
			<li>
				<key>\</key>
				<value>
					<shapeOrDef>Ship_LifeSupport</shapeOrDef>
				</value>
			</li>
			<li>
				<key>]</key>
				<value>
					<shapeOrDef>CommsConsole</shapeOrDef>
				</value>
			</li>
			<li>
				<key>^</key>
				<value>
					<shapeOrDef>ShipPilotSeatMini</shapeOrDef>
				</value>
			</li>
			<li>
				<key>_</key>
				<value>
					<shapeOrDef>Ship_SensorCluster</shapeOrDef>
				</value>
			</li>
			<li>
				<key>`</key>
				<value>
					<shapeOrDef>ShipShuttleBay</shapeOrDef>
				</value>
			</li>
			<li>
				<key>a</key>
				<value>
					<shapeOrDef>ShipSalvageBay</shapeOrDef>
				</value>
			</li>
			<li>
				<key>b</key>
				<value>
					<shapeOrDef>ShipAirlockBeam</shapeOrDef>
				</value>
			</li>
			<li>
				<key>c</key>
				<value>
					<shapeOrDef>TableMachining</shapeOrDef>
				</value>
			</li>
			<li>
				<key>d</key>
				<value>
					<shapeOrDef>Stool</shapeOrDef>
					<stuff>Steel</stuff>
				</value>
			</li>
			<li>
				<key>e</key>
				<value>
					<shapeOrDef>ShipHeatManifold</shapeOrDef>
				</value>
			</li>
			<li>
				<key>f</key>
				<value>
					<shapeOrDef>ShipInside_PassiveVent</shapeOrDef>
				</value>
			</li>
			<li>
				<key>g</key>
				<value>
					<shapeOrDef>Table1x2c</shapeOrDef>
					<stuff>Steel</stuff>
				</value>
			</li>
			<li>
				<key>h</key>
				<value>
					<shapeOrDef>DiningChair</shapeOrDef>
					<stuff>Steel</stuff>
				</value>
			</li>
			<li>
				<key>i</key>
				<value>
					<shapeOrDef>PersonalShuttle</shapeOrDef>
				</value>
			</li>
			<li>
				<key>j</key>
				<value>
					<shapeOrDef>FlatscreenTelevision</shapeOrDef>
				</value>
			</li>
			<li>
				<key>k</key>
				<value>
					<shapeOrDef>ElectricStove</shapeOrDef>
				</value>
			</li>
			<li>
				<key>l</key>
				<value>
					<shapeOrDef>Armchair</shapeOrDef>
					<stuff>Synthread</stuff>
				</value>
			</li>
			<li>
				<key>m</key>
				<value>
					<shapeOrDef>ShipConsoleScience</shapeOrDef>
				</value>
			</li>
			<li>
				<key>n</key>
				<value>
					<shapeOrDef>SpaceCrew</shapeOrDef>
				</value>
			</li>
			<li>
				<key>o</key>
				<value>
					<shapeOrDef>SpaceCrewMarine</shapeOrDef>
				</value>
			</li>
			<li>
				<key>p</key>
				<value>
					<shapeOrDef>ComponentIndustrial</shapeOrDef>
				</value>
			</li>
			<li>
				<key>q</key>
				<value>
					<shapeOrDef>MedicineIndustrial</shapeOrDef>
				</value>
			</li>
			<li>
				<key>r</key>
				<value>
					<shapeOrDef>ShuttleFuelPods</shapeOrDef>
				</value>
			</li>
			<li>
				<key>s</key>
				<value>
					<shapeOrDef>Chemfuel</shapeOrDef>
				</value>
			</li>
			<li>
				<key>t</key>
				<value>
					<shapeOrDef>MealSurvivalPack</shapeOrDef>
				</value>
			</li>
			<li>
				<key>u</key>
				<value>
					<shapeOrDef>HullFoam</shapeOrDef>
				</value>
			</li>
			<li>
				<key>v</key>
				<value>
					<shapeOrDef>Apparel_SpaceSuitHelmet</shapeOrDef>
				</value>
			</li>
			<li>
				<key>w</key>
				<value>
					<shapeOrDef>Apparel_SpaceSuitBody</shapeOrDef>
				</value>
			</li>
			<li>
				<key>x</key>
				<value>
					<shapeOrDef>OrbitalTradeBeacon</shapeOrDef>
				</value>
			</li>
			<li>
				<key>y</key>
				<value>
					<shapeOrDef>Lighting_MURWallLight</shapeOrDef>
				</value>
			</li>
			<li>
				<key>z</key>
				<value>
					<shapeOrDef>SterileTile</shapeOrDef>
				</value>
			</li>
		</symbolTable>
		<bigString>44,22,0,?|44,21,0,?|44,20,0,?|44,19,0,?|44,17,0,?|44,16,0,?|44,15,0,?|44,14,0,?|40,14,0,@|40,15,0,@|40,16,0,@|40,17,0,@|38,18,0,@|35,19,0,@|34,19,0,@|33,19,0,@|32,19,0,@|31,19,0,@|30,19,0,@|29,19,0,@|27,19,0,@|26,19,0,@|25,19,0,@|24,19,0,@|23,19,0,@|22,19,0,@|21,19,0,@|20,19,0,@|19,19,0,@|17,19,0,@|10,19,0,@|10,18,2,A|9,17,2,A|8,17,0,@|7,17,0,@|6,17,0,@|5,17,0,@|4,17,0,@|3,17,0,@|2,17,0,@|1,18,0,@|0,20,0,@|0,21,0,A|1,21,0,@|1,22,0,A|1,29,0,@|0,30,0,@|1,32,0,@|1,33,0,A|2,33,0,@|3,33,0,@|3,31,0,?|3,30,0,?|3,28,0,?|4,28,0,?|4,27,0,?|4,26,0,?|4,25,0,?|4,24,0,?|4,23,0,?|4,22,0,?|4,20,0,?|4,19,0,?|3,19,0,?|5,19,0,?|6,19,0,?|6,20,0,?|6,22,0,?|6,23,0,?|6,24,0,?|6,25,0,?|6,26,0,?|6,27,0,?|6,28,0,?|5,30,0,?|5,31,0,?|5,33,0,@|6,33,0,@|7,33,0,@|7,31,0,?|7,30,0,?|8,30,0,?|8,28,0,?|8,27,0,?|8,26,0,?|8,24,0,?|8,23,0,?|8,22,0,?|8,20,0,?|8,19,0,?|10,22,0,?|10,23,0,?|10,24,0,?|10,25,0,?|10,27,0,?|10,28,0,?|10,30,0,@|10,31,0,@|13,30,0,@|13,28,0,?|13,27,0,?|13,25,0,?|13,24,0,?|13,23,0,?|13,22,0,?|15,22,0,?|15,23,0,?|15,24,0,?|15,26,0,?|15,27,0,?|15,28,0,?|15,30,0,@|16,30,0,@|17,28,1,B|17,22,1,B|18,21,0,?|19,21,0,?|19,22,0,?|18,23,0,?|19,23,0,?|20,23,0,?|20,24,0,?|20,25,0,?|19,25,0,?|19,26,0,?|18,27,0,?|19,27,0,?|20,27,0,?|20,28,0,?|20,29,0,?|19,29,0,?|19,31,0,@|18,31,0,@|20,31,0,@|21,31,0,@|22,29,0,?|22,28,0,?|22,26,0,?|22,25,0,?|22,24,0,?|22,22,0,?|22,21,0,?|21,21,0,?|23,21,0,?|24,21,0,?|24,22,0,?|23,23,0,?|24,23,0,?|26,21,0,?|26,22,0,?|26,24,0,?|24,25,0,?|24,26,0,?|23,27,0,?|24,27,0,?|26,28,0,?|26,26,0,?|28,26,0,?|28,25,0,?|29,25,0,?|29,24,0,?|29,23,0,?|29,21,0,?|28,21,0,?|29,22,0,?|30,22,0,?|31,21,0,?|31,22,0,?|31,23,0,?|31,24,0,?|31,25,0,?|31,26,0,?|30,26,0,?|30,27,0,?|29,27,0,?|28,28,0,?|28,29,0,?|26,31,0,@|25,31,0,@|24,31,0,@|23,31,0,@|27,31,0,@|29,31,0,@|30,31,0,@|30,29,0,?|31,29,0,?|34,21,0,?|35,21,0,?|35,22,0,?|34,23,0,?|35,23,0,?|36,23,0,?|36,24,0,?|36,25,0,?|35,25,0,?|35,26,0,?|34,27,0,?|34,28,0,?|34,29,0,?|32,31,0,@|33,31,0,@|34,31,0,@|35,31,0,@|36,29,0,?|36,28,0,?|36,27,0,?|38,31,0,@|37,31,0,@|38,32,0,@|40,33,0,@|40,30,0,?|40,29,0,?|40,28,0,?|40,27,0,?|40,26,0,?|40,25,0,?|40,24,0,?|40,23,0,?|40,22,0,?|40,21,0,?|40,20,0,?|41,19,0,?|42,17,0,?|42,16,0,?|42,15,0,?|42,14,0,?|42,19,0,?|42,20,0,?|42,21,0,?|41,20,0,?|41,21,0,?|41,22,0,?|41,28,0,?|41,29,0,?|42,29,0,?|42,30,0,?|42,31,0,?|42,33,0,?|42,34,0,?|40,35,0,@|40,36,0,@|46,36,0,?|46,35,0,?|46,34,0,?|46,33,0,?|46,31,0,?|46,30,0,?|46,29,0,?|46,28,0,?|46,27,0,?|46,26,0,?|46,25,0,?|46,24,0,?|48,20,0,?|48,19,0,?|46,14,0,?|46,15,0,?|46,16,0,?|46,17,0,?|46,19,0,?|49,24,0,?|49,25,0,?|48,25,0,?|48,26,0,?|48,27,0,?|48,28,0,?|48,29,0,?|48,30,0,?|48,31,0,?|51,32,0,@|51,30,0,?|51,29,0,?|51,28,0,?|51,26,0,?|51,25,0,?|52,25,0,?|52,24,0,?|52,22,0,?|52,21,0,?|52,20,0,?|54,19,0,@|56,19,0,@|54,23,0,@|53,29,1,B|54,31,0,@|55,31,0,@|56,31,0,@|54,27,0,@|55,27,0,@|56,27,0,@|55,23,0,@|56,23,0,@|55,19,0,@|53,21,1,B|53,25,1,B|52,26,0,?|52,28,0,?|52,29,0,?|52,30,0,?|49,33,0,@|49,31,0,?|49,30,0,?|49,29,0,?|49,28,0,?|49,27,0,?|49,26,0,?|50,25,1,B|51,24,0,?|51,22,0,?|51,21,0,?|51,20,0,?|51,18,0,@|47,17,0,?|49,17,0,@|47,19,0,?|49,19,0,?|48,21,0,?|47,21,0,?|46,21,0,?|46,22,0,?|46,23,0,?|47,23,0,?|48,23,0,?|47,22,0,?|48,22,0,?|49,20,0,?|47,20,0,?|46,20,0,?|48,24,0,?|49,23,0,?|49,22,0,?|49,21,0,?|47,24,0,?|47,25,0,?|47,26,0,?|47,27,0,?|45,28,0,?|47,28,0,?|45,29,0,?|44,29,0,?|44,30,0,?|44,31,0,?|44,33,0,?|44,34,0,?|44,35,0,?|43,35,0,?|43,36,0,?|42,36,0,?|44,36,0,?|47,29,0,?|45,30,0,?|47,30,0,?|45,31,0,?|47,31,0,?|45,33,0,?|47,33,0,?|45,34,0,?|45,35,0,?|45,36,0,?|42,35,0,?|43,34,0,?|43,33,0,?|43,31,0,?|43,30,0,?|43,29,0,?|41,30,0,?|41,31,0,?|40,34,0,@|36,31,0,@|35,29,0,?|35,27,0,?|35,28,0,?|36,26,0,?|35,24,0,?|36,22,0,?|36,21,0,?|34,22,0,?|34,24,0,?|34,25,0,?|34,26,0,?|31,28,0,?|31,31,0,@|28,31,0,@|29,28,0,?|29,29,0,?|30,28,0,?|31,27,0,?|30,21,0,?|28,22,0,?|30,23,0,?|30,24,0,?|30,25,0,?|29,26,0,?|28,27,0,?|24,29,0,?|26,29,0,?|26,27,0,?|24,28,0,?|26,25,0,?|28,24,0,?|28,23,0,?|26,23,0,?|24,24,0,?|21,22,0,?|22,23,0,?|23,22,0,?|21,23,0,?|23,24,0,?|23,25,0,?|21,26,0,?|22,27,0,?|23,26,0,?|21,27,0,?|23,28,0,?|23,29,0,?|22,31,0,@|21,29,0,?|21,28,0,?|19,28,0,?|20,26,0,?|21,25,0,?|21,24,0,?|19,24,0,?|20,22,0,?|20,21,0,?|18,22,0,?|18,24,0,?|18,25,0,?|18,26,0,?|18,28,0,?|18,29,0,?|17,31,0,@|16,28,0,?|16,27,0,?|16,26,0,?|16,25,0,?|16,24,0,?|16,23,0,?|16,22,0,?|12,22,0,?|14,22,0,?|12,23,0,?|14,23,0,?|12,24,0,?|14,24,0,?|12,25,0,?|14,25,0,?|14,26,0,?|12,27,0,?|14,27,0,?|12,28,0,?|14,28,0,?|14,30,0,@|12,30,0,@|11,30,0,@|11,28,0,?|11,27,0,?|11,25,0,?|11,24,0,?|11,23,0,?|11,22,0,?|9,22,0,?|9,23,0,?|9,24,0,?|9,25,0,?|9,26,0,?|9,27,0,?|9,28,0,?|8,31,0,?|8,33,0,@|6,31,0,?|6,30,0,?|7,28,0,?|7,27,0,?|7,26,0,?|7,25,0,?|7,24,0,?|7,23,0,?|7,22,0,?|7,20,0,?|7,19,0,?|3,20,0,?|5,20,0,?|3,22,0,?|5,22,0,?|5,23,0,?|5,24,0,?|5,25,0,?|5,26,0,?|5,27,0,?|5,28,0,?|4,30,0,?|4,31,0,?|4,33,0,@|1,31,0,@|1,30,0,@|3,27,0,?|3,26,0,?|3,25,0,?|3,24,0,?|3,23,0,?|1,20,0,@|1,19,0,@|10,20,0,@|11,20,0,@|12,20,0,@|13,20,0,@|14,20,0,@|15,20,0,@|16,20,0,@|18,19,0,@|28,19,0,@|36,19,0,@|37,19,0,@|38,19,0,@|43,14,0,?|45,14,0,?|43,15,0,?|45,15,0,?|43,16,0,?|45,16,0,?|43,17,0,?|45,17,0,?|43,19,0,?|45,19,0,?|43,20,0,?|45,20,0,?|43,21,0,?|45,21,0,?|44,23,0,?|43,23,0,?|42,23,0,?|42,24,0,?|42,25,0,?|42,26,0,?|42,27,0,?|43,27,0,?|44,27,0,?|44,26,0,?|44,25,0,?|43,26,0,?|43,25,0,?|43,24,0,?|44,24,0,?|45,22,0,?|43,22,0,?|42,22,0,?|41,23,0,?|41,24,0,?|41,25,0,?|41,26,0,?|41,27,0,?|42,28,0,?|43,28,0,?|44,28,0,?|45,27,0,?|45,26,0,?|45,25,0,?|45,24,0,?|45,23,0,?|15,25,0,?|13,26,0,?|12,26,0,?|11,26,0,?|10,26,0,?|8,25,0,?|0,18,0,C|0,31,0,D|3,30,0,E|3,19,0,E|7,19,0,E|7,30,0,E|36,18,3,F|15,19,3,F|12,19,3,G|12,31,1,F|53,18,3,G|53,32,1,F|36,32,1,G|15,31,1,G|55,21,3,H|55,25,3,H|55,29,3,H|3,25,3,I|4,25,3,I|5,25,3,I|6,25,3,I|13,25,3,I|12,25,3,I|11,25,3,I|10,25,3,I|9,25,3,I|8,25,3,I|7,25,3,I|15,25,3,J|1,25,3,K|56,32,0,@|55,32,0,@|56,18,0,@|55,18,0,@|55,33,1,C|56,17,3,D|53,26,0,L|53,27,0,L|53,28,0,L|53,22,0,L|53,23,0,L|53,24,0,L|50,23,0,L|50,22,0,L|50,24,0,L|50,27,0,L|50,28,0,L|48,36,0,L|36,27,0,L|35,27,0,L|34,27,0,L|36,23,0,L|35,23,0,L|34,23,0,L|17,24,0,L|17,26,0,L|17,29,0,L|16,29,0,L|15,29,0,L|14,29,0,L|13,29,0,L|12,29,0,L|11,29,0,L|10,29,0,L|9,29,0,L|17,21,0,L|16,21,0,L|15,21,0,L|14,21,0,L|13,21,0,L|12,21,0,L|11,21,0,L|10,21,0,L|9,21,0,L|2,28,0,L|2,29,0,L|2,21,0,L|2,22,0,L|50,18,0,L|50,19,0,L|50,20,0,L|50,30,0,L|50,31,0,L|50,32,0,L|49,32,0,L|48,32,0,L|47,32,0,L|45,32,0,L|49,18,0,L|48,18,0,L|47,18,0,L|45,18,0,L|48,16,0,L|48,17,0,L|48,33,0,L|48,34,0,L|39,19,0,L|41,18,0,L|40,18,0,L|41,32,0,L|40,32,0,L|39,31,0,L|41,14,0,L|41,15,0,L|41,16,0,L|41,17,0,L|41,33,0,L|41,34,0,L|41,35,0,L|41,36,0,L|38,20,0,L|37,20,0,L|36,20,0,L|35,20,0,L|34,20,0,L|33,20,0,L|32,20,0,L|31,20,0,L|30,20,0,L|29,20,0,L|28,20,0,L|27,20,0,L|26,20,0,L|25,20,0,L|24,20,0,L|23,20,0,L|22,20,0,L|21,20,0,L|20,20,0,L|19,20,0,L|18,20,0,L|17,20,0,L|38,30,0,L|37,30,0,L|36,30,0,L|35,30,0,L|34,30,0,L|33,30,0,L|32,30,0,L|31,30,0,L|30,30,0,L|29,30,0,L|28,30,0,L|27,30,0,L|26,30,0,L|25,30,0,L|24,30,0,L|23,30,0,L|22,30,0,L|21,30,0,L|20,30,0,L|19,30,0,L|18,30,0,L|17,30,0,L|48,14,0,L|52,19,0,L|51,19,0,L|53,19,0,L|53,20,0,L|53,30,0,L|53,31,0,L|52,31,0,L|51,31,0,L|3,21,0,?|3,29,0,?|4,21,0,?|4,29,0,?|5,21,0,?|5,29,0,?|6,21,0,?|6,29,0,?|7,21,0,?|7,29,0,?|8,21,0,?|8,29,0,?|2,18,0,L|3,18,0,L|4,18,0,L|5,18,0,L|6,18,0,L|7,18,0,L|8,18,0,L|9,18,0,L|2,19,0,L|2,20,0,L|9,19,0,L|9,20,0,L|9,30,0,L|9,31,0,L|9,32,0,L|2,32,0,L|3,32,0,L|4,32,0,L|5,32,0,L|6,32,0,L|7,32,0,L|8,32,0,L|2,30,0,L|2,31,0,L|3,29,1,M|7,29,1,M|7,21,1,M|3,21,1,M|19,25,0,N|21,23,0,L|21,24,0,L|21,25,0,L|21,26,0,L|21,27,0,L|18,21,1,M|18,29,1,M|35,25,0,O|37,23,0,L|37,24,0,L|37,25,0,L|37,26,0,L|37,27,0,L|33,21,0,?|33,22,0,?|33,23,0,?|33,24,0,?|33,25,0,?|33,26,0,?|33,27,0,?|33,28,0,?|33,29,0,?|38,21,0,?|38,22,0,?|38,23,0,?|38,24,0,?|38,25,0,?|38,26,0,?|38,27,0,?|38,28,0,?|38,29,0,?|39,21,0,?|39,22,0,?|39,23,0,?|39,24,0,?|39,25,0,?|39,26,0,?|39,27,0,?|39,28,0,?|39,29,0,?|37,21,1,B|37,29,1,B|33,27,0,B|33,23,0,B|45,8,0,?|45,7,0,?|46,7,0,?|46,6,0,?|46,5,0,?|46,4,0,?|46,3,0,?|46,2,0,L|46,1,0,@|45,6,0,?|44,6,0,?|43,6,0,?|43,5,0,?|43,4,0,?|43,3,0,?|43,2,0,L|44,5,0,?|46,8,0,?|46,9,0,?|46,10,0,?|47,10,0,?|48,10,0,?|48,9,0,?|48,8,0,?|48,7,0,?|48,6,0,?|48,5,0,?|48,4,0,?|48,3,0,?|48,2,0,L|48,1,0,@|47,9,0,?|47,8,0,?|45,9,0,?|44,9,0,?|43,9,0,?|42,9,0,?|42,8,0,?|42,7,0,?|41,7,0,?|41,6,0,?|41,5,0,?|41,4,0,?|41,3,0,?|43,10,0,?|43,11,0,?|45,11,0,?|44,11,0,?|43,8,0,?|44,10,0,?|44,8,0,?|44,7,0,?|47,7,0,?|47,6,0,?|47,5,0,?|45,5,0,?|47,4,0,?|45,4,0,?|47,3,0,?|45,3,0,?|47,2,0,L|45,2,0,L|47,1,0,@|45,1,0,@|43,7,0,?|42,6,0,?|42,5,0,?|44,4,0,?|42,4,0,?|44,3,0,?|42,3,0,?|44,2,0,L|44,1,0,@|46,11,0,?|45,10,0,?|47,11,0,?|46,13,0,?|49,13,0,@|50,13,0,@|53,14,1,G|55,14,0,@|56,14,0,@|57,14,0,@|58,14,0,@|59,14,0,@|60,14,0,@|61,14,2,A|60,13,2,A|59,11,3,H|57,10,1,B|56,10,0,?|56,9,0,?|56,8,0,?|56,7,0,?|56,6,0,?|56,5,0,?|56,4,0,?|56,3,0,?|56,0,0,@|57,9,0,L|57,11,0,L|57,12,0,L|54,12,0,L|53,11,0,?|50,9,0,?|50,8,0,?|54,11,0,L|55,11,0,?|60,9,0,@|59,7,3,H|59,9,0,@|58,9,0,@|59,13,0,@|58,13,0,@|51,12,0,L|50,12,0,L|49,12,0,L|49,10,0,?|48,11,0,?|49,9,0,?|49,8,0,?|49,7,0,?|49,6,0,?|50,6,0,?|54,6,0,L|54,5,0,L|54,3,0,L|54,2,0,L|50,1,0,@|53,0,3,F|51,2,0,L|50,2,0,L|53,6,0,?|53,5,0,?|53,4,0,?|53,3,0,?|52,6,0,?|52,5,0,?|52,4,0,?|52,3,0,?|51,5,0,?|51,4,0,?|51,3,0,?|50,4,0,?|50,3,0,?|51,6,0,?|50,5,0,?|49,5,0,?|49,4,0,?|49,3,0,?|49,2,0,L|49,1,0,@|42,10,0,?|41,10,0,?|40,10,0,?|39,10,0,?|38,10,0,?|37,10,0,?|33,10,0,@|32,10,3,D|31,11,0,@|31,12,1,C|33,12,0,@|33,13,0,A|34,13,0,@|35,13,0,@|36,13,0,@|37,13,0,@|38,13,0,@|39,13,0,@|40,13,0,@|40,12,0,L|39,12,0,L|38,12,0,L|35,12,0,L|32,11,0,@|33,11,0,@|34,8,0,@|35,8,0,L|36,8,0,?|37,8,0,?|38,8,0,?|39,8,0,?|40,8,0,?|39,7,0,?|39,6,0,?|38,6,0,?|37,6,0,?|36,6,0,?|35,6,0,L|34,6,0,@|36,4,0,?|38,4,0,?|39,4,0,?|39,3,0,?|39,2,0,L|38,2,0,L|38,1,0,@|37,1,0,@|36,1,0,@|35,1,0,@|34,1,0,@|33,2,0,@|35,2,0,L|39,1,0,@|38,3,0,?|37,2,0,L|36,2,0,L|37,3,0,?|37,4,0,?|36,3,0,?|35,5,0,L|36,5,0,?|37,5,0,?|38,5,0,?|39,5,0,?|38,7,0,?|37,7,0,?|36,7,0,?|35,7,0,L|34,7,0,@|35,9,0,L|36,12,0,L|37,12,0,L|37,9,0,?|36,9,0,?|37,11,0,?|36,11,0,?|36,10,0,?|38,11,0,?|38,9,0,?|39,11,0,?|39,9,0,?|40,11,0,?|40,9,0,?|41,11,0,?|41,9,0,?|41,8,0,?|40,6,0,?|40,5,0,?|40,4,0,?|40,3,0,?|42,11,0,?|43,13,0,?|44,13,0,?|45,13,0,?|56,11,0,?|55,10,0,?|55,9,0,?|57,8,0,L|55,8,0,?|57,7,1,B|55,7,0,?|57,6,0,L|55,6,0,?|57,5,0,L|55,5,0,?|57,4,1,B|59,3,3,H|60,1,0,P|60,0,0,@|59,0,0,@|58,0,0,@|61,0,0,P|59,1,0,@|58,1,0,@|55,4,0,?|57,3,0,L|55,3,0,?|57,2,0,L|57,1,0,L|57,0,0,@|55,0,0,@|50,10,0,?|50,11,0,?|51,8,0,?|51,9,0,?|51,10,0,?|51,11,0,?|52,8,0,?|52,9,0,?|52,10,0,?|52,11,0,?|53,8,0,?|53,9,0,?|53,10,0,?|50,7,0,?|51,7,0,?|52,7,0,?|53,7,0,?|54,8,0,L|49,11,0,?|58,5,0,@|59,5,0,@|60,5,0,@|43,41,0,?|43,40,0,?|44,40,0,?|44,39,0,?|44,37,0,?|43,39,0,?|42,39,0,?|41,39,0,?|44,41,0,?|44,42,0,?|44,43,0,?|45,43,0,?|46,43,0,?|46,42,0,?|46,41,0,?|46,40,0,?|46,39,0,?|46,37,0,?|45,42,0,?|45,41,0,?|43,42,0,?|42,42,0,?|41,42,0,?|40,42,0,?|40,41,0,?|40,40,0,?|39,40,0,?|39,39,0,?|39,38,0,L|39,37,0,@|41,43,0,?|41,44,0,?|41,45,0,?|42,45,0,?|43,45,0,?|43,44,0,?|42,44,0,?|41,41,0,?|42,43,0,?|42,41,0,?|42,40,0,?|45,40,0,?|45,39,0,?|45,37,0,?|43,37,0,?|41,40,0,?|40,39,0,?|40,38,0,L|40,37,0,@|44,44,0,?|43,43,0,?|45,44,0,?|45,45,0,?|45,46,0,?|44,46,0,?|44,47,0,?|43,47,0,?|42,47,0,?|41,47,0,?|40,47,0,?|39,47,0,?|38,47,0,?|37,47,0,?|36,48,0,L|36,49,0,@|37,49,0,@|38,49,0,@|39,49,0,@|44,49,0,@|45,49,0,@|45,48,0,L|46,48,0,L|46,47,0,?|47,47,0,?|47,46,0,?|47,45,0,?|47,44,0,?|48,44,0,?|48,43,0,?|48,42,0,?|48,41,0,?|48,40,0,?|48,39,0,?|37,48,0,L|37,45,0,?|38,45,0,?|39,45,0,?|39,44,0,?|39,43,0,?|38,43,0,?|38,42,0,?|38,41,0,?|37,41,0,?|37,40,0,?|36,39,0,?|38,44,0,?|37,44,0,?|36,44,0,?|35,44,0,L|35,45,0,L|34,49,0,@|34,49,0,?|35,43,0,L|34,43,0,@|34,42,0,@|34,37,0,@|35,42,0,L|36,42,0,?|36,43,0,?|36,45,0,?|37,46,0,?|36,47,0,?|36,46,0,?|38,48,0,L|38,46,0,?|39,48,0,L|39,46,0,?|40,46,0,?|43,48,0,L|44,48,0,L|45,47,0,?|46,46,0,?|46,45,0,?|47,43,0,?|46,44,0,?|47,42,0,?|47,41,0,?|47,40,0,?|47,39,0,?|39,42,0,?|39,41,0,?|38,40,0,?|38,39,0,?|38,38,0,L|38,37,0,@|37,37,0,@|36,37,0,@|40,44,0,?|41,46,0,?|40,45,0,?|42,46,0,?|44,45,0,?|43,46,0,?|35,48,0,L|35,49,0,@|46,49,0,@|47,49,0,@|48,49,0,@|49,49,0,@|50,49,0,@|53,50,1,G|55,50,0,@|56,50,0,@|57,50,0,@|58,50,0,@|59,50,0,@|60,50,0,@|61,50,2,A|60,49,2,A|59,47,3,H|57,46,1,B|56,46,0,?|55,46,0,?|54,46,0,?|53,46,0,?|52,43,0,?|52,42,0,?|50,39,0,?|51,43,0,?|50,43,0,?|53,47,0,?|53,45,0,?|53,44,0,?|52,47,0,?|52,46,0,?|52,45,0,?|52,44,0,?|51,47,0,?|51,46,0,?|51,45,0,?|51,44,0,?|50,47,0,?|50,46,0,?|50,45,0,?|50,44,0,?|54,47,0,?|54,47,0,L|54,48,0,L|54,45,0,?|54,45,0,L|55,47,0,?|55,45,0,?|55,44,0,?|56,44,0,?|57,44,0,L|59,43,3,H|57,42,0,L|56,42,0,?|55,42,0,?|55,41,0,?|55,40,0,?|56,40,0,?|57,40,1,B|57,39,0,L|57,38,0,L|57,36,0,@|56,39,0,?|55,39,0,?|54,38,0,L|53,36,3,F|56,41,0,?|57,41,0,L|60,41,0,@|59,39,3,H|60,37,0,P|60,36,0,@|59,36,0,@|61,36,0,P|59,37,0,@|59,41,0,@|58,41,0,@|57,43,1,B|56,43,0,?|55,43,0,?|54,43,0,?|56,47,0,?|56,45,0,?|57,45,0,L|57,47,0,L|57,48,0,L|60,45,0,@|59,45,0,@|58,45,0,@|59,49,0,@|58,49,0,@|57,49,0,L|56,49,0,L|51,48,0,L|50,48,0,L|49,48,0,L|48,48,0,L|47,48,0,L|48,47,0,?|48,46,0,?|48,45,0,?|49,44,0,?|49,43,0,?|49,42,0,?|49,41,0,?|49,40,0,?|49,39,0,?|49,38,0,L|49,37,0,@|50,37,0,@|37,43,0,?|37,42,0,?|36,41,0,?|36,40,0,?|37,39,0,?|36,38,0,L|37,38,0,L|34,44,0,@|33,48,0,@|35,41,0,L|33,41,0,A|33,40,0,@|31,40,1,C|32,39,0,@|32,38,3,D|31,39,0,@|33,39,0,@|35,38,0,L|33,38,0,@|35,37,0,@|33,37,3,A|53,43,0,?|54,44,0,?|54,44,0,L|49,47,0,?|49,46,0,?|49,45,0,?|50,40,0,?|50,41,0,?|50,42,0,?|51,39,0,?|51,40,0,?|51,41,0,?|51,42,0,?|52,39,0,?|52,40,0,?|52,41,0,?|53,39,0,?|53,40,0,?|53,41,0,?|53,42,0,?|50,38,0,L|51,38,0,L|54,39,0,?|54,39,0,L|54,40,0,?|54,41,0,?|54,42,0,?|54,42,0,L|58,37,0,@|58,36,0,@|56,36,0,@|55,36,0,@|33,9,2,P|33,1,2,P|33,45,2,P|33,49,0,A|33,5,0,A|31,3,0,@|32,3,0,@|33,3,0,@|33,4,0,@|33,46,0,@|33,47,0,@|31,47,0,@|32,47,0,@|31,48,1,C|31,4,1,C|32,2,3,D|32,46,3,D|55,38,0,?|56,38,0,?|55,48,0,?|56,48,0,?|55,2,0,?|56,2,0,?|55,12,0,?|56,12,0,?|55,2,0,Q|55,11,0,Q|55,38,0,Q|55,47,0,Q|54,49,0,L|55,49,0,L|54,37,0,L|55,37,0,L|56,37,0,L|57,37,0,L|54,13,0,L|55,13,0,L|56,13,0,L|57,13,0,L|54,1,0,L|55,1,0,L|56,1,0,L|41,13,0,L|41,37,0,L|44,12,0,L|45,12,0,L|46,12,0,L|47,12,0,L|44,38,0,L|45,38,0,L|46,38,0,L|47,38,0,L|48,35,0,L|48,37,0,L|48,13,0,L|48,15,0,L|49,14,0,@|49,15,0,@|49,16,0,@|49,34,0,@|49,35,0,@|49,36,0,@|42,13,0,?|42,37,0,?|47,13,0,?|47,14,0,?|47,15,0,?|47,16,0,?|47,34,0,?|47,35,0,?|47,36,0,?|47,37,0,?|50,21,0,L|50,29,0,L|51,23,0,?|51,27,0,?|52,23,0,?|52,27,0,?|45,19,0,L|45,22,0,L|45,23,0,L|46,23,0,L|47,23,0,L|49,23,0,L|45,27,0,L|46,27,0,L|47,27,0,L|48,27,0,L|49,27,0,L|45,28,0,L|45,31,0,L|42,22,0,L|42,28,0,L|38,22,0,L|39,22,0,L|40,22,0,L|41,22,0,L|38,28,0,L|39,28,0,L|40,28,0,L|41,28,0,L|44,28,0,L|44,22,0,L|45,24,0,L|45,26,0,L|45,25,1,B|43,28,0,B|43,22,0,B|45,30,1,B|45,20,1,B|44,13,0,L|44,14,0,L|44,16,0,L|44,17,0,L|44,18,0,L|44,32,0,L|44,33,0,L|44,34,0,L|44,36,0,L|44,37,0,L|46,26,1,R|48,26,1,R|49,24,3,R|47,24,3,R|49,28,0,S|47,28,0,S|47,37,2,S|45,37,2,S|47,13,0,S|45,13,0,S|47,17,2,S|45,17,2,S|47,33,0,S|45,33,0,S|44,15,1,B|44,35,1,B|49,22,2,T|47,22,2,T|48,22,2,U|48,19,0,V|46,19,0,V|47,31,2,V|49,31,2,W|46,37,2,X|46,17,2,X|46,13,0,X|48,28,0,X|46,33,0,X|52,30,2,V|51,20,0,V|51,23,1,V|51,28,1,V|51,7,0,Y|51,43,0,Y|45,4,0,Z|45,9,0,Z|45,40,0,Z|45,45,0,Z|55,42,1,V|55,45,1,V|55,9,1,V|55,6,1,V|54,7,0,L|54,43,0,L|54,40,1,B|54,46,1,B|54,10,1,B|54,4,1,B|23,27,0,[|23,23,0,\|22,25,0,L|23,25,0,L|24,25,0,L|27,21,0,?|27,22,0,?|27,23,0,?|27,24,0,?|27,25,0,?|27,26,0,?|27,27,0,?|27,28,0,?|27,29,0,?|25,22,0,L|25,23,0,L|25,24,0,L|25,26,0,L|25,27,0,L|25,28,0,L|25,21,1,B|25,29,1,B|43,39,0,L|43,40,0,L|43,41,0,L|43,42,0,L|43,44,0,L|43,45,0,L|43,46,0,L|43,47,0,L|43,3,0,L|43,4,0,L|43,5,0,L|43,6,0,L|43,8,0,L|43,9,0,L|43,10,0,L|43,11,0,L|42,18,0,B|42,12,0,B|42,32,0,B|42,38,0,B|43,32,0,L|43,18,0,L|44,19,3,R|43,31,1,R|27,27,2,]|26,24,1,^|29,27,0,_|26,22,0,L|27,22,0,L|28,22,0,L|29,22,0,L|31,22,0,L|26,28,0,L|27,28,0,L|28,28,0,L|29,28,0,L|31,28,0,L|32,22,0,L|32,23,0,L|32,24,0,L|32,25,0,L|32,27,0,L|32,28,0,L|30,22,0,B|32,21,1,B|32,29,1,B|30,28,0,B|43,7,1,B|43,43,1,B|40,7,0,?|40,43,0,?|39,43,0,`|39,7,0,a|41,1,0,B|41,49,0,B|40,49,2,b|42,49,2,b|42,1,0,b|40,1,0,b|40,47,0,L|41,47,0,L|40,3,0,L|41,3,0,L|42,47,0,B|42,3,0,B|41,2,0,?|42,2,0,?|41,48,0,?|42,48,0,?|43,1,0,L|43,49,0,L|39,11,0,c|39,10,0,d|38,39,0,V|40,39,0,V|39,47,2,V|38,3,0,V|39,15,0,G|50,35,2,G|39,35,0,F|50,15,2,F|39,17,0,@|50,17,0,@|50,33,0,@|39,33,0,@|38,33,0,A|51,17,2,A|51,33,0,P|38,17,2,P|50,47,1,M|50,39,1,M|50,3,1,M|50,11,1,M|52,2,0,?|52,12,0,?|53,2,0,?|53,12,0,?|52,38,0,?|52,48,0,?|53,38,0,?|53,48,0,?|5,19,0,E|5,30,0,E|52,47,0,e|52,2,0,e|52,11,0,e|51,13,0,L|52,13,0,L|53,13,0,L|51,1,0,L|52,1,0,L|53,1,0,L|51,49,0,L|52,49,0,L|53,49,0,L|51,37,0,L|52,37,0,L|53,37,0,L|49,11,2,V|48,39,0,V|52,38,0,e|39,20,0,L|39,18,0,L|39,32,0,L|39,30,0,L|40,19,0,?|40,31,0,?|41,19,3,R|40,31,1,R|36,22,2,V|35,28,0,V|25,25,1,f|45,21,1,f|45,29,1,f|48,23,0,f|50,26,1,f|48,12,2,f|48,38,0,f|41,38,0,f|41,12,2,f|40,2,1,f|40,48,1,f|54,41,1,f|54,9,1,f|43,12,0,f|43,38,2,f|37,28,3,f|37,22,3,f|46,18,2,f|46,32,0,f|32,26,1,f|17,23,1,f|17,27,3,f|17,25,0,L|39,24,1,g|39,25,2,h|38,24,1,h|39,23,0,h|40,23,0,h|41,24,3,h|44,26,3,V|10,32,0,P|9,33,0,P|1,17,2,P|1,28,2,P|0,29,2,P|39,7,0,i|39,8,0,i|44,23,3,j|39,27,0,k|42,27,2,V|28,24,2,l|27,24,3,l|27,25,0,l|30,25,1,l|31,25,3,m|30,23,0,n|29,24,0,n|29,25,0,n|29,26,0,n|47,20,0,n|42,25,0,n|42,20,0,o|43,24,0,o|42,30,0,o|48,30,0,o|46,35,0,o|43,35,0,o|42,10,0,o|34,21,0,o|41,40,0,o|56,43,0,o|41,25,0,o|42,8,0,o|21,22,0,o|48,43,0,o|42,43,0,o|35,22,0,p|48,19,0,q|47,19,0,q|49,11,0,r|48,11,0,r|49,39,0,r|52,20,0,s|51,22,0,s|51,23,0,s|51,27,0,s|51,30,0,s|55,41,0,s|55,42,0,s|55,8,0,s|55,6,0,s|44,26,0,t|44,27,0,t|35,28,0,u|41,39,0,u|39,3,0,v|40,39,0,v|38,3,0,w|38,39,0,w|35,39,0,?|35,40,0,?|35,46,0,?|35,47,0,?|35,3,0,?|35,4,0,?|35,10,0,?|35,11,0,?|35,10,0,Q|35,3,0,Q|35,39,0,Q|35,46,0,Q|34,38,0,L|34,39,0,L|34,40,0,L|34,41,0,L|34,45,0,L|34,46,0,L|34,47,0,L|34,48,0,L|34,9,0,L|34,10,0,L|34,11,0,L|34,12,0,L|34,2,0,L|34,3,0,L|34,4,0,L|34,5,0,L|36,9,0,x|50,24,1,y|34,27,0,y|34,23,2,y|12,29,2,y|12,21,0,y|2,28,1,y|2,22,1,y|41,15,1,y|41,35,1,y|21,23,2,y|21,27,0,y|43,2,3,y|49,12,2,y|39,12,2,y|39,2,0,y|39,38,0,y|39,48,2,y|43,48,3,y|49,38,0,y|48,35,3,y|48,15,3,y|47,23,2,y|47,27,0,y|48,27,2,y|42,22,2,y|42,28,0,y|41,28,2,y|54,7,1,y|54,43,1,y|29,22,2,y|28,28,2,y|29,28,0,y|32,25,1,y|46,19,0,z|47,19,0,z|48,19,0,z|49,19,0,z|46,20,0,z|47,20,0,z|48,20,0,z|49,20,0,z|46,21,0,z|47,21,0,z|48,21,0,z|49,21,0,z|46,22,0,z|47,22,0,z|48,22,0,z|49,22,0,z</bigString>
	</EnemyShipDef>
</Defs>