<?xml version="1.0" encoding="utf-8"?>
<Defs>
	<EnemyShipDef>
		<defName>HaulerModular</defName>
		<saveSysVer>2</saveSysVer>
		<offsetX>75</offsetX>
		<offsetZ>105</offsetZ>
		<sizeX>100</sizeX>
		<sizeZ>38</sizeZ>
		<label>Modular hauler</label>
		<combatPoints>217</combatPoints>
		<randomTurretPoints>60</randomTurretPoints>
		<cargoValue>2500</cargoValue>
		<neverAttacks>True</neverAttacks>
		<tradeShip>True</tradeShip>
		<core>
			<shapeOrDef>ShipPilotSeatMini</shapeOrDef>
			<x>2</x>
			<z>19</z>
			<rot>1</rot>
		</core>
		<symbolTable>
			<li>
				<key>?</key>
				<value>
					<shapeOrDef>RawCorn</shapeOrDef>
				</value>
			</li>
			<li>
				<key>@</key>
				<value>
					<shapeOrDef>ShipHullTile</shapeOrDef>
				</value>
			</li>
			<li>
				<key>A</key>
				<value>
					<shapeOrDef>Lighting_MURWallLight</shapeOrDef>
				</value>
			</li>
			<li>
				<key>B</key>
				<value>
					<shapeOrDef>ShipInside_PassiveVent</shapeOrDef>
				</value>
			</li>
			<li>
				<key>C</key>
				<value>
					<shapeOrDef>ShipAirlock</shapeOrDef>
				</value>
			</li>
			<li>
				<key>D</key>
				<value>
					<shapeOrDef>Ship_Beam</shapeOrDef>
				</value>
			</li>
			<li>
				<key>E</key>
				<value>
					<shapeOrDef>SpaceCrew</shapeOrDef>
				</value>
			</li>
			<li>
				<key>F</key>
				<value>
					<shapeOrDef>Ship_Beam_Unpowered</shapeOrDef>
				</value>
			</li>
			<li>
				<key>G</key>
				<value>
					<shapeOrDef>Ship_Corner_OneOne</shapeOrDef>
				</value>
			</li>
			<li>
				<key>H</key>
				<value>
					<shapeOrDef>Lighting_MURWallLight</shapeOrDef>
					<color>RGBA(0.000, 1.000, 0.000, 1.000)</color>
				</value>
			</li>
			<li>
				<key>I</key>
				<value>
					<shapeOrDef>Ship_Corner_OneOneFlip</shapeOrDef>
				</value>
			</li>
			<li>
				<key>J</key>
				<value>
					<shapeOrDef>Lighting_MURWallLight</shapeOrDef>
					<color>RGBA(1.000, 0.000, 0.000, 1.000)</color>
				</value>
			</li>
			<li>
				<key>K</key>
				<value>
					<shapeOrDef>Ship_Thruster</shapeOrDef>
				</value>
			</li>
			<li>
				<key>L</key>
				<value>
					<shapeOrDef>SpaceCrewMarineHeavy</shapeOrDef>
				</value>
			</li>
			<li>
				<key>M</key>
				<value>
					<shapeOrDef>Lighting_MURWallSunLight</shapeOrDef>
				</value>
			</li>
			<li>
				<key>N</key>
				<value>
					<shapeOrDef>PowerConduit</shapeOrDef>
				</value>
			</li>
			<li>
				<key>O</key>
				<value>
					<shapeOrDef>OrbitalTradeBeacon</shapeOrDef>
				</value>
			</li>
			<li>
				<key>P</key>
				<value>
					<shapeOrDef>ShipHeatConduit</shapeOrDef>
				</value>
			</li>
			<li>
				<key>Q</key>
				<value>
					<shapeOrDef>SpaceCrewMarine</shapeOrDef>
				</value>
			</li>
			<li>
				<key>R</key>
				<value>
					<shapeOrDef>FirefoamPopper</shapeOrDef>
				</value>
			</li>
			<li>
				<key>S</key>
				<value>
					<shapeOrDef>Cargo</shapeOrDef>
					<width>11</width>
					<height>3</height>
				</value>
			</li>
			<li>
				<key>T</key>
				<value>
					<shapeOrDef>Shelf</shapeOrDef>
					<stuff>Steel</stuff>
				</value>
			</li>
			<li>
				<key>U</key>
				<value>
					<shapeOrDef>Ship_Corner_OneTwoFlip</shapeOrDef>
				</value>
			</li>
			<li>
				<key>V</key>
				<value>
					<shapeOrDef>Ship_Corner_OneTwo</shapeOrDef>
				</value>
			</li>
			<li>
				<key>W</key>
				<value>
					<shapeOrDef>ShipCapacitorSmall</shapeOrDef>
				</value>
			</li>
			<li>
				<key>X</key>
				<value>
					<shapeOrDef>ShipHeatsink</shapeOrDef>
				</value>
			</li>
			<li>
				<key>Y</key>
				<value>
					<shapeOrDef>ShipTurret_Laser</shapeOrDef>
				</value>
			</li>
			<li>
				<key>Z</key>
				<value>
					<shapeOrDef>TableMachining</shapeOrDef>
				</value>
			</li>
			<li>
				<key>[</key>
				<value>
					<shapeOrDef>Ship_Corner_OneThree</shapeOrDef>
				</value>
			</li>
			<li>
				<key>\</key>
				<value>
					<shapeOrDef>Ship_Corner_OneThreeFlip</shapeOrDef>
				</value>
			</li>
			<li>
				<key>]</key>
				<value>
					<shapeOrDef>ElectricSmelter</shapeOrDef>
				</value>
			</li>
			<li>
				<key>^</key>
				<value>
					<shapeOrDef>HydroponicsBasin</shapeOrDef>
				</value>
			</li>
			<li>
				<key>_</key>
				<value>
					<shapeOrDef>Ship_ComputerCore</shapeOrDef>
				</value>
			</li>
			<li>
				<key>`</key>
				<value>
					<shapeOrDef>Ship_LifeSupport</shapeOrDef>
				</value>
			</li>
			<li>
				<key>a</key>
				<value>
					<shapeOrDef>ShipCombatShieldGenerator</shapeOrDef>
					<radius>47</radius>
				</value>
			</li>
			<li>
				<key>b</key>
				<value>
					<shapeOrDef>Ship_Reactor</shapeOrDef>
				</value>
			</li>
			<li>
				<key>c</key>
				<value>
					<shapeOrDef>Ship_Engine</shapeOrDef>
				</value>
			</li>
			<li>
				<key>d</key>
				<value>
					<shapeOrDef>Chemfuel</shapeOrDef>
				</value>
			</li>
			<li>
				<key>e</key>
				<value>
					<shapeOrDef>Armchair</shapeOrDef>
					<stuff>Synthread</stuff>
				</value>
			</li>
			<li>
				<key>f</key>
				<value>
					<shapeOrDef>CommsConsole</shapeOrDef>
				</value>
			</li>
			<li>
				<key>g</key>
				<value>
					<shapeOrDef>ShipConsoleScience</shapeOrDef>
				</value>
			</li>
			<li>
				<key>h</key>
				<value>
					<shapeOrDef>Dresser</shapeOrDef>
					<stuff>Steel</stuff>
				</value>
			</li>
			<li>
				<key>i</key>
				<value>
					<shapeOrDef>Bed</shapeOrDef>
					<stuff>Steel</stuff>
				</value>
			</li>
			<li>
				<key>j</key>
				<value>
					<shapeOrDef>Ship_CryptosleepCasket</shapeOrDef>
				</value>
			</li>
			<li>
				<key>k</key>
				<value>
					<shapeOrDef>Ship_SensorCluster</shapeOrDef>
				</value>
			</li>
			<li>
				<key>l</key>
				<value>
					<shapeOrDef>EndTable</shapeOrDef>
					<stuff>Steel</stuff>
				</value>
			</li>
			<li>
				<key>m</key>
				<value>
					<shapeOrDef>ShipAirlockBeam</shapeOrDef>
				</value>
			</li>
			<li>
				<key>n</key>
				<value>
					<shapeOrDef>DiningChair</shapeOrDef>
					<stuff>Steel</stuff>
				</value>
			</li>
			<li>
				<key>o</key>
				<value>
					<shapeOrDef>DoubleBed</shapeOrDef>
					<stuff>Steel</stuff>
				</value>
			</li>
			<li>
				<key>p</key>
				<value>
					<shapeOrDef>HospitalBed</shapeOrDef>
					<stuff>Steel</stuff>
				</value>
			</li>
			<li>
				<key>q</key>
				<value>
					<shapeOrDef>ElectricStove</shapeOrDef>
				</value>
			</li>
			<li>
				<key>r</key>
				<value>
					<shapeOrDef>Table2x2c</shapeOrDef>
					<stuff>Steel</stuff>
				</value>
			</li>
			<li>
				<key>s</key>
				<value>
					<shapeOrDef>FlatscreenTelevision</shapeOrDef>
				</value>
			</li>
			<li>
				<key>t</key>
				<value>
					<shapeOrDef>ChessTable</shapeOrDef>
					<stuff>Steel</stuff>
				</value>
			</li>
			<li>
				<key>u</key>
				<value>
					<shapeOrDef>VitalsMonitor</shapeOrDef>
				</value>
			</li>
			<li>
				<key>v</key>
				<value>
					<shapeOrDef>ShipCombatShieldGenerator</shapeOrDef>
					<radius>45</radius>
				</value>
			</li>
			<li>
				<key>w</key>
				<value>
					<shapeOrDef>Gun_ChainShotgun</shapeOrDef>
				</value>
			</li>
			<li>
				<key>x</key>
				<value>
					<shapeOrDef>Apparel_SpaceSuitHelmet</shapeOrDef>
				</value>
			</li>
			<li>
				<key>y</key>
				<value>
					<shapeOrDef>MealFine</shapeOrDef>
				</value>
			</li>
			<li>
				<key>z</key>
				<value>
					<shapeOrDef>MealSurvivalPack</shapeOrDef>
				</value>
			</li>
			<li>
				<key>{</key>
				<value>
					<shapeOrDef>Beer</shapeOrDef>
				</value>
			</li>
			<li>
				<key>}</key>
				<value>
					<shapeOrDef>RawRice</shapeOrDef>
				</value>
			</li>
			<li>
				<key>~</key>
				<value>
					<shapeOrDef>RawPotatoes</shapeOrDef>
				</value>
			</li>
			<li>
				<key></key>
				<value>
					<shapeOrDef>Apparel_SpaceSuitBody</shapeOrDef>
					<stuff>Synthread</stuff>
				</value>
			</li>
			<li>
				<key></key>
				<value>
					<shapeOrDef>MedicineIndustrial</shapeOrDef>
				</value>
			</li>
			<li>
				<key></key>
				<value>
					<shapeOrDef>ComponentIndustrial</shapeOrDef>
				</value>
			</li>
			<li>
				<key></key>
				<value>
					<shapeOrDef>ComponentSpacer</shapeOrDef>
				</value>
			</li>
			<li>
				<key></key>
				<value>
					<shapeOrDef>Lighting_MURWallLight</shapeOrDef>
					<color>RGBA(0.000, 0.000, 1.000, 1.000)</color>
				</value>
			</li>
			<li>
				<key></key>
				<value>
					<shapeOrDef>ShipHeatManifold</shapeOrDef>
				</value>
			</li>
			<li>
				<key></key>
				<value>
					<shapeOrDef>ShipPartTurretLarge</shapeOrDef>
				</value>
			</li>
			<li>
				<key></key>
				<value>
					<shapeOrDef>ShipSalvageBay</shapeOrDef>
				</value>
			</li>
			<li>
				<key></key>
				<value>
					<shapeOrDef>ShipShuttleBay</shapeOrDef>
				</value>
			</li>
			<li>
				<key></key>
				<value>
					<shapeOrDef>PersonalShuttle</shapeOrDef>
				</value>
			</li>
			<li>
				<key></key>
				<value>
					<shapeOrDef>Cargo</shapeOrDef>
					<width>5</width>
					<height>5</height>
				</value>
			</li>
			<li>
				<key></key>
				<value>
					<shapeOrDef>SterileTile</shapeOrDef>
				</value>
			</li>
		</symbolTable>
		<bigString>79,17,0,?|79,16,0,?|81,16,0,?|82,19,0,@|84,19,0,@|82,18,0,@|81,18,0,@|80,18,0,@|80,19,0,@|80,20,0,@|81,20,0,@|81,21,0,@|82,21,0,@|83,21,0,@|84,21,0,@|85,21,0,@|85,20,0,@|86,20,0,@|86,20,1,A|86,20,3,B|86,19,0,@|86,19,1,C|86,18,0,@|86,18,0,D|86,18,3,A|86,17,0,@|86,17,0,D|86,16,0,@|86,16,0,D|86,15,0,@|86,15,0,D|86,14,0,@|86,14,0,D|86,13,0,@|86,13,0,D|86,12,0,@|86,12,0,D|86,11,0,D|86,10,0,@|86,9,0,@|80,17,0,@|79,17,0,@|79,16,0,@|80,16,0,@|81,16,0,@|81,15,0,@|81,15,0,D|81,14,0,@|81,13,0,D|81,12,0,D|81,11,0,D|80,15,0,D|81,17,0,@|82,17,0,@|83,17,0,@|84,17,0,@|84,16,0,@|83,15,0,@|83,15,0,D|83,14,0,@|84,14,0,@|83,13,0,@|84,15,0,@|84,15,0,D|83,16,0,@|83,18,0,@|84,18,0,@|85,19,0,@|84,20,0,@|83,20,0,@|82,20,0,@|81,19,0,@|79,18,0,@|78,18,3,B|77,18,0,@|74,19,0,@|74,20,0,@|75,20,0,@|75,19,0,@|76,19,0,@|76,17,0,@|76,17,0,E|76,16,0,@|74,16,0,@|75,16,0,@|77,16,0,@|76,15,0,D|76,14,0,F|75,14,0,@|74,14,0,@|75,13,0,@|76,13,0,F|75,17,0,@|74,17,0,@|73,17,0,@|72,17,0,D|71,17,0,@|70,17,0,@|70,18,0,@|70,16,0,@|70,15,0,D|71,15,0,D|71,14,3,G|71,18,0,@|71,16,0,@|72,18,0,D|72,18,1,H|72,19,1,C|72,20,3,B|72,21,0,D|72,22,0,D|71,22,0,@|71,23,0,D|70,23,0,D|71,24,3,I|72,24,0,D|72,25,1,B|73,25,0,@|74,25,0,@|74,24,0,@|73,24,0,@|73,23,0,C|72,23,0,D|73,22,0,@|74,22,0,@|77,23,0,D|78,23,0,D|77,22,0,@|76,22,0,@|75,22,0,@|73,21,0,@|72,16,0,D|75,18,0,@|74,18,0,@|76,18,0,@|77,19,0,@|77,17,0,@|78,19,1,C|79,19,0,@|80,21,0,@|79,20,0,@|81,22,0,@|79,21,0,@|79,22,0,@|80,22,0,@|82,22,0,@|82,23,0,@|82,23,0,C|82,24,0,@|81,24,0,@|80,24,1,B|80,25,0,D|81,27,0,D|82,29,0,F|83,31,0,D|84,33,0,D|85,35,0,D|86,35,0,D|86,34,0,@|87,34,0,@|86,33,0,@|85,34,2,D|85,33,0,D|85,32,0,@|87,31,0,@|87,30,0,@|87,29,0,@|87,28,0,@|86,30,0,@|85,30,0,@|84,30,0,@|84,29,0,@|85,27,0,D|85,26,0,@|85,25,0,@|84,27,0,D|84,28,0,@|86,31,0,@|85,31,0,@|84,32,2,D|84,31,2,B|83,30,2,D|83,30,1,J|83,29,0,D|82,28,0,F|82,27,0,D|81,26,0,D|81,25,0,D|82,25,0,@|83,24,0,@|83,23,0,@|83,23,0,D|81,23,0,@|81,23,0,D|80,23,0,D|79,23,0,D|78,22,0,D|78,21,0,D|83,22,0,@|86,22,0,@|86,22,0,D|86,23,0,@|86,23,0,D|87,23,0,@|88,21,0,@|88,20,0,@|88,19,0,@|88,18,0,@|88,18,0,E|88,17,0,@|88,16,0,@|88,15,0,@|87,21,0,@|91,26,0,@|91,25,0,@|91,24,0,@|91,23,0,@|91,22,0,@|90,26,0,@|90,25,0,@|90,24,0,@|90,23,0,@|90,22,0,@|89,26,0,@|89,25,0,@|89,24,0,@|89,23,0,@|89,22,0,@|88,26,0,@|88,25,0,@|88,24,0,@|88,22,0,@|87,26,0,@|87,25,0,@|87,24,0,@|88,23,0,@|87,22,0,@|84,22,0,@|86,21,0,@|86,21,0,D|85,22,0,@|87,20,0,@|87,19,0,@|87,18,0,@|85,18,0,@|87,17,0,@|85,17,0,@|87,16,0,@|85,16,0,@|87,15,0,@|85,15,0,@|85,15,0,D|87,14,0,@|85,14,0,@|87,13,0,@|85,13,0,@|87,12,0,@|85,12,0,@|87,11,0,D|85,11,0,D|87,10,0,@|85,10,0,@|83,9,0,D|83,8,2,D|83,8,1,J|83,7,0,D|84,7,0,B|85,7,0,@|87,7,0,@|88,7,0,@|89,8,0,@|89,9,0,@|90,10,0,@|92,10,0,D|92,11,0,D|93,11,0,@|93,13,0,@|93,15,0,@|93,17,0,@|92,17,0,@|92,17,0,D|92,18,0,@|92,18,1,B|91,18,0,@|90,18,0,@|90,19,0,@|90,20,0,@|91,20,0,@|92,20,0,@|92,20,3,B|92,21,0,@|92,21,0,D|93,21,0,@|93,20,0,@|91,19,0,@|92,19,0,@|92,19,1,C|93,18,0,@|93,16,0,@|93,14,0,@|93,8,0,@|92,8,1,C|92,7,0,D|92,7,1,J|91,7,0,@|91,6,0,@|91,5,0,@|89,4,0,@|87,4,0,@|86,3,0,D|86,4,0,@|87,3,0,D|87,5,0,@|88,3,0,D|88,4,0,@|89,3,0,D|89,2,0,F|90,2,0,F|91,2,0,D|92,2,0,D|92,3,0,D|93,3,0,@|93,4,0,@|93,2,0,D|92,1,0,F|91,1,0,K|92,4,0,D|91,3,0,D|90,3,0,D|90,4,0,@|90,5,0,@|92,5,0,D|91,4,0,@|92,6,0,D|92,6,3,J|93,6,0,@|93,7,0,@|93,7,0,L|93,9,0,@|93,12,0,@|93,12,2,B|93,10,0,@|92,9,0,D|91,8,0,@|91,9,0,@|91,10,0,@|89,10,0,@|90,9,0,@|90,8,0,@|90,7,0,@|90,6,0,@|89,5,0,@|88,5,0,@|89,6,0,@|88,8,0,@|89,7,0,@|88,6,0,@|87,6,0,@|86,5,0,@|85,5,0,D|84,5,0,D|86,6,0,@|86,7,0,@|85,6,0,@|84,6,2,D|83,10,0,D|85,8,0,@|84,8,0,@|84,9,0,@|84,10,0,@|87,9,0,@|86,8,0,@|87,8,0,@|88,9,0,@|88,10,0,@|85,9,0,@|78,17,0,D|79,15,0,D|78,15,0,D|78,16,0,D|82,16,0,@|82,15,0,@|82,15,0,C|82,14,0,@|80,14,1,B|82,13,0,@|80,13,0,D|82,12,0,@|82,11,0,D|82,9,0,F|82,10,0,F|83,12,0,@|84,12,0,@|84,13,0,@|83,11,0,D|84,11,0,D|73,18,0,@|73,19,0,@|74,21,0,@|73,20,0,@|76,20,0,@|77,20,0,@|78,20,0,D|78,20,1,A|77,21,0,@|76,21,0,@|75,21,0,@|74,15,0,D|73,15,0,C|75,15,0,D|75,15,0,M|77,15,0,D|73,16,0,@|74,13,0,@|74,12,0,@|74,12,0,N|73,12,0,@|72,12,0,D|72,13,1,B|72,11,0,D|72,11,1,A|70,11,1,F|69,11,0,@|68,11,0,@|67,11,0,@|66,11,0,@|65,11,0,@|64,11,0,@|63,11,0,@|62,11,0,@|61,11,0,@|60,11,0,@|59,11,0,@|58,11,0,@|57,11,0,@|56,11,1,D|55,11,0,D|55,11,2,A|54,11,0,D|54,12,0,D|54,14,0,D|54,15,0,D|54,16,0,D|54,17,0,D|54,19,1,C|54,20,0,D|54,21,0,D|54,22,0,D|54,23,0,D|54,24,0,D|54,26,0,D|54,27,0,D|54,28,1,C|54,29,0,D|54,30,0,D|54,31,0,D|54,32,0,D|54,34,0,F|54,35,0,F|54,36,0,F|55,36,0,F|56,36,0,F|57,36,0,F|58,36,0,F|59,36,0,F|60,36,0,F|61,36,0,F|62,36,0,F|63,36,0,F|64,36,0,F|65,36,0,F|66,36,0,F|67,36,0,F|68,36,0,F|69,36,0,F|70,36,0,F|71,36,0,F|72,36,0,F|73,36,0,I|73,35,0,F|73,33,0,F|72,33,0,F|71,33,2,F|70,33,2,F|69,33,2,F|68,33,2,F|71,34,0,G|71,32,3,G|72,34,0,F|72,32,0,D|72,31,0,D|73,31,0,@|74,30,0,F|75,29,0,F|75,28,0,F|74,28,0,@|73,28,0,@|72,28,1,C|72,27,0,D|72,27,1,A|74,27,0,@|74,29,0,F|73,29,0,@|74,31,0,F|73,30,0,@|72,30,0,D|73,32,0,F|74,32,0,F|73,34,0,F|72,35,0,F|71,35,2,I|67,35,2,G|67,34,0,I|66,34,2,F|65,34,0,G|65,33,2,F|64,33,2,F|63,33,2,F|62,33,2,F|61,33,2,F|60,33,2,F|59,33,2,F|58,33,2,F|57,33,2,F|56,33,2,F|59,34,0,G|60,34,2,F|61,34,0,I|66,33,2,F|66,35,2,F|65,35,2,I|61,35,2,G|60,35,2,F|59,35,2,I|55,35,2,G|55,34,0,I|55,33,2,F|55,32,1,I|55,29,0,D|56,29,1,D|56,30,1,D|56,31,3,I|57,31,1,D|58,31,1,D|59,31,1,D|60,31,1,D|60,31,2,A|61,31,1,D|62,31,1,D|63,31,1,D|64,31,1,D|65,31,1,D|66,31,1,D|66,31,2,A|67,31,1,D|68,31,1,D|69,31,1,D|70,31,1,G|70,30,1,F|70,29,1,F|69,29,0,@|68,29,0,@|67,29,0,@|66,29,0,@|65,29,0,@|64,29,0,@|63,29,0,@|62,29,0,@|61,29,0,@|60,29,0,@|59,29,0,@|58,29,0,@|58,28,0,@|57,28,0,@|57,27,0,@|56,26,1,D|56,25,3,G|57,25,1,F|58,25,1,F|58,26,0,@|59,26,0,@|59,27,0,@|60,27,0,@|61,27,0,@|62,27,0,@|63,27,0,@|64,27,0,@|65,27,0,@|66,27,0,@|66,26,0,@|66,25,1,F|65,26,0,@|64,26,0,@|64,25,1,F|63,25,1,F|62,25,1,F|63,26,0,@|62,26,0,O|62,26,0,@|61,26,0,@|60,26,0,@|60,25,1,F|59,25,1,F|57,26,1,F|58,27,0,@|59,28,0,@|60,28,0,@|61,28,0,@|62,28,0,@|63,28,0,@|64,28,0,@|65,28,0,@|66,28,0,@|67,28,0,@|68,28,0,@|68,27,0,@|69,27,0,@|69,26,1,F|70,26,1,F|70,25,1,I|69,25,1,F|68,25,1,F|68,26,0,@|69,28,0,@|70,28,1,F|69,30,1,F|68,30,0,@|67,30,0,@|66,30,0,@|65,30,0,@|64,30,0,@|63,30,0,@|62,30,0,@|61,30,0,@|60,30,0,@|59,30,0,@|58,30,0,@|57,30,1,D|57,29,0,@|56,28,1,C|55,28,0,@|55,27,0,D|55,27,0,A|55,24,1,G|55,23,0,D|56,23,0,D|57,23,0,D|58,23,0,D|59,23,0,D|60,23,0,D|61,23,0,D|62,23,0,D|63,23,0,D|64,23,0,D|65,23,0,D|66,23,0,D|67,23,0,D|68,23,0,D|68,23,2,A|65,22,0,@|64,22,0,@|64,21,0,@|62,21,0,@|61,21,0,@|60,21,0,@|61,19,0,@|62,19,0,@|63,18,0,@|63,19,0,@|62,18,0,@|61,18,0,@|61,17,0,@|61,16,0,@|62,16,0,@|63,16,0,N|63,16,0,@|64,16,0,@|65,16,0,@|65,15,0,D|64,15,0,D|63,15,0,D|62,15,0,D|61,15,0,D|60,15,0,D|59,15,0,D|58,15,0,D|57,15,0,D|60,16,0,@|59,16,0,@|58,16,0,@|57,16,0,@|56,16,0,@|60,19,0,@|60,18,0,@|60,17,0,@|59,20,0,@|59,19,0,@|59,18,0,@|59,17,0,@|58,21,0,@|58,20,0,@|58,19,0,@|58,18,0,@|57,20,0,@|57,19,0,@|57,18,0,@|56,21,0,@|56,20,0,@|56,19,0,@|56,18,0,@|56,17,0,@|60,20,0,@|61,20,0,@|62,20,0,@|63,20,0,@|63,21,0,P|63,21,0,@|64,20,0,@|63,22,0,P|63,22,0,@|62,22,0,@|61,22,0,@|60,22,0,@|59,22,0,@|58,22,0,@|57,22,0,@|56,22,0,@|55,22,0,@|55,21,0,@|55,20,0,@|55,19,0,@|55,18,0,@|55,17,0,@|55,16,0,@|55,15,0,D|55,14,1,I|54,10,1,C|54,9,0,D|55,9,0,D|57,9,0,@|58,9,0,@|59,9,0,@|60,9,0,@|61,9,0,@|62,9,0,@|63,9,0,@|64,9,0,@|65,9,0,@|66,9,0,@|67,9,0,@|68,9,0,@|69,9,0,@|70,9,1,F|72,9,0,D|73,9,0,@|73,10,0,@|74,10,0,@|75,11,0,F|75,9,0,F|74,6,0,F|73,6,0,F|72,6,0,D|71,6,3,I|71,5,0,F|70,5,0,F|69,5,0,F|68,5,0,F|67,5,0,F|66,5,0,F|65,5,0,F|64,5,0,F|63,5,0,F|62,5,0,F|61,5,0,F|61,4,2,G|61,3,0,I|61,2,0,F|65,4,2,I|65,3,0,G|66,3,0,F|67,3,0,I|67,2,0,F|68,2,0,F|69,2,0,F|70,2,0,F|71,2,0,F|71,3,0,G|72,3,0,F|73,3,0,F|73,2,2,G|72,2,0,F|66,2,0,F|65,2,0,F|64,2,0,F|63,2,0,F|66,4,0,F|67,4,2,G|71,4,2,I|72,7,0,D|72,5,0,F|73,7,0,@|73,5,0,F|74,7,0,F|74,8,0,F|75,10,0,F|74,9,0,F|73,8,0,@|72,8,0,D|70,8,1,F|70,7,1,I|69,7,1,F|68,7,1,F|67,7,1,F|66,7,1,F|65,7,1,F|64,7,1,F|63,7,1,F|62,7,1,F|61,7,1,F|60,7,1,F|59,7,1,F|58,7,1,F|57,7,1,F|56,7,3,G|69,8,1,F|68,8,0,@|67,8,0,@|66,8,0,@|65,8,0,@|64,8,0,@|63,8,0,@|62,8,0,O|62,8,0,@|61,8,0,@|60,8,0,@|59,8,0,@|58,8,0,@|57,8,1,F|56,8,1,D|54,8,0,D|54,7,0,D|54,6,0,D|55,6,1,G|55,5,0,F|56,5,0,F|57,5,0,F|58,5,0,F|59,5,0,F|59,4,2,I|59,3,0,G|59,2,0,F|58,2,0,F|57,2,0,F|56,2,0,F|55,2,0,F|54,2,0,F|54,3,0,F|54,4,0,F|55,3,0,I|55,4,2,G|55,10,0,@|56,12,1,D|56,13,3,I|57,13,1,D|58,13,1,D|59,13,1,D|60,13,1,D|60,13,2,A|61,13,1,D|62,13,1,D|63,13,1,D|64,13,1,D|65,13,1,D|66,13,1,D|66,13,2,A|67,13,1,D|68,13,1,D|69,13,1,D|70,13,1,G|56,10,1,C|57,12,1,D|57,10,0,@|58,12,0,@|58,10,0,@|59,12,0,@|59,10,0,@|60,12,0,@|60,10,0,@|61,12,0,@|61,10,0,@|62,12,0,@|62,10,0,@|63,12,0,@|63,10,0,@|64,12,0,@|64,10,0,@|65,12,0,@|65,10,0,@|66,12,0,@|66,10,0,@|67,12,0,@|67,10,0,@|68,12,0,@|68,10,0,@|69,12,1,F|69,10,0,@|70,12,1,F|70,10,1,F|72,10,1,C|73,11,0,@|74,11,0,@|75,12,0,F|73,14,0,@|73,13,0,@|76,12,0,F|69,17,0,@|66,17,0,@|66,18,0,@|66,19,0,@|66,20,0,@|66,21,0,@|67,17,0,@|67,18,0,@|67,19,0,@|67,20,0,@|67,21,0,@|68,17,0,@|68,18,0,@|68,20,0,@|68,21,0,@|69,18,0,@|69,19,0,@|69,20,0,@|69,21,0,@|70,19,0,@|70,20,0,@|70,21,0,@|66,16,0,@|67,16,0,@|67,15,0,D|68,15,0,D|68,15,0,A|68,16,0,@|68,16,0,Q|69,16,0,@|71,19,0,@|71,20,0,@|71,21,0,@|70,22,0,@|69,22,0,@|68,22,0,@|67,22,0,@|66,22,0,@|65,21,0,@|65,20,0,@|65,19,0,@|65,19,0,O|65,18,0,@|65,17,0,@|69,15,0,D|72,15,0,D|72,14,0,D|69,23,0,D|72,26,0,D|73,26,0,@|75,25,0,@|74,26,0,@|74,26,0,N|75,24,0,@|74,23,0,D|75,23,0,D|75,23,2,M|76,24,0,F|76,25,0,F|75,26,0,F|76,23,0,D|87,35,0,D|88,35,0,D|89,35,0,D|89,36,0,F|91,37,2,K|92,37,0,F|93,37,2,K|93,33,0,@|92,32,0,D|92,32,3,J|91,32,0,@|90,32,0,@|89,32,0,@|89,30,0,@|90,30,0,@|91,30,0,@|92,30,1,C|93,30,0,@|93,28,0,@|92,27,0,D|93,26,0,@|93,26,0,B|93,23,0,@|93,24,0,@|93,25,0,@|92,28,0,D|91,28,0,@|89,28,0,@|90,28,0,@|93,27,0,@|93,29,0,@|92,29,0,D|91,29,0,@|90,29,0,@|89,29,0,@|88,32,0,@|89,33,0,@|90,34,0,@|91,35,0,D|92,35,0,D|93,35,0,@|92,34,0,D|91,34,0,@|89,31,0,@|90,33,0,@|90,31,0,@|91,33,0,@|91,31,0,@|92,31,0,D|92,31,1,J|93,31,0,@|92,33,0,D|93,34,0,@|93,32,0,@|93,36,0,D|92,36,0,D|91,36,0,D|90,36,0,F|90,35,0,D|89,34,0,@|88,36,0,F|87,33,0,@|86,32,0,@|87,32,0,@|88,33,0,@|88,34,0,@|88,31,0,@|88,30,0,@|88,29,0,@|86,29,0,@|86,28,0,@|86,27,0,D|87,27,0,D|88,28,0,@|85,29,0,@|85,28,0,@|83,28,0,D|86,26,0,@|86,26,0,D|84,26,0,@|83,25,0,@|83,26,0,@|84,24,0,@|84,25,0,@|85,24,0,@|84,23,0,@|84,23,0,D|85,23,0,@|85,23,0,D|86,24,0,@|86,24,0,D|86,25,0,@|86,25,0,D|83,27,0,D|82,26,0,@|89,21,0,@|90,21,0,@|91,21,0,@|92,22,0,@|92,22,0,D|92,22,1,J|92,23,0,@|92,23,0,D|92,24,0,@|92,24,0,D|92,25,0,@|92,25,0,D|92,26,0,@|92,26,0,D|91,27,0,D|90,27,0,D|89,27,0,D|88,27,0,D|89,20,0,@|89,19,0,@|89,18,0,@|89,17,0,@|89,16,0,@|88,12,0,@|88,13,0,@|88,14,0,@|89,12,0,@|89,13,0,@|89,14,0,@|89,15,0,@|90,12,0,@|90,13,0,@|90,14,0,@|90,15,0,@|90,16,0,@|91,12,0,@|91,13,0,@|91,14,0,@|91,15,0,@|91,16,0,@|88,11,0,D|89,11,0,D|90,11,0,D|91,11,0,D|92,12,0,@|92,12,0,D|92,13,0,@|92,13,0,D|92,14,0,@|92,14,0,D|92,15,0,@|92,15,0,D|92,16,0,@|92,16,0,D|92,16,1,J|91,17,0,@|90,17,0,@|93,22,0,@|93,19,0,@|85,4,2,D|85,3,0,D|88,2,0,F|93,5,0,@|93,1,0,K|67,33,2,F|76,26,0,F|75,27,0,F|73,27,0,@|72,29,0,D|70,27,1,F|67,27,0,@|67,26,0,@|67,25,1,F|65,25,1,F|61,25,1,F|64,18,0,@|64,19,0,@|62,17,0,@|63,17,0,N|63,17,0,@|64,17,0,@|64,17,0,R|66,15,0,D|56,15,0,D|60,5,0,F|60,4,0,F|60,3,0,F|62,2,0,F|60,2,0,F|72,4,0,F|73,4,0,F|54,18,0,D|54,25,0,D|54,13,0,D|58,9,0,S|58,27,0,S|83,17,0,Q|83,19,0,@|79,17,1,T|81,16,3,T|81,9,0,U|79,24,0,V|80,26,0,V|81,28,0,V|82,30,0,V|83,32,0,V|84,34,0,V|82,25,0,W|88,21,2,T|87,17,0,T|82,7,0,U|93,11,1,T|93,14,1,T|93,16,1,T|93,4,1,T|93,6,1,T|83,5,0,U|84,3,0,U|79,13,0,U|82,13,2,W|80,11,0,U|73,30,0,W|74,27,0,W|63,21,0,T|74,10,0,W|73,7,0,W|93,33,1,T|93,28,1,T|93,23,1,T|93,25,1,T|93,35,1,T|90,21,1,W|90,17,1,W|63,17,2,T|86,9,0,X|74,13,0,Y|74,24,0,Y|86,28,0,X|84,28,0,X|84,9,0,X|88,9,0,X|90,9,0,X|90,28,0,X|88,28,0,X|84,16,2,Z|77,13,2,[|86,36,1,\|84,22,0,]|86,2,3,[|89,1,3,[|74,34,2,\|75,31,2,\|76,28,2,\|76,10,2,[|75,7,2,[|74,4,2,[|77,25,2,\|89,37,1,\|75,18,1,^|75,20,1,^|75,16,1,^|75,22,1,^|84,13,0,_|84,25,0,`|63,19,0,a|89,24,0,b|89,14,0,b|95,1,3,U|94,2,0,D|94,3,0,@|94,4,0,@|94,5,0,@|94,6,0,@|94,7,0,@|94,8,0,@|94,9,0,@|94,10,0,@|94,11,0,@|94,13,0,@|94,14,0,@|94,15,0,@|94,16,0,@|94,17,0,@|94,18,0,@|94,19,0,@|94,20,0,@|94,21,0,@|94,22,0,@|94,23,0,@|94,24,0,@|94,25,0,@|94,26,0,@|94,26,0,C|94,27,0,@|94,28,0,@|94,29,0,@|94,30,0,@|94,31,0,@|94,32,0,@|94,33,0,@|94,34,0,@|94,35,0,@|94,36,0,D|94,37,1,V|95,2,0,D|95,3,0,D|95,4,1,C|95,5,0,D|95,6,0,D|95,7,1,C|95,8,0,D|95,9,0,D|95,10,0,D|95,11,0,D|95,12,0,D|95,13,0,D|95,14,1,C|95,15,0,D|95,16,0,D|95,17,1,C|95,18,0,D|95,19,0,D|95,20,0,D|95,21,1,C|95,22,0,D|95,23,0,D|95,24,1,C|95,25,0,D|95,26,0,D|95,27,0,D|95,28,0,D|95,29,0,D|95,30,0,D|95,31,1,C|95,32,0,D|95,33,0,D|95,34,1,C|95,35,0,D|95,36,0,D|97,1,3,[|96,2,0,F|97,4,3,c|97,7,3,c|96,9,0,F|97,10,1,\|97,11,3,[|96,12,0,F|97,14,3,c|97,17,3,c|96,19,0,F|97,21,3,c|97,24,3,c|96,26,0,F|97,27,1,\|97,28,3,[|96,29,0,F|97,31,3,c|97,34,3,c|96,36,0,F|97,37,1,\|97,2,0,F|97,9,0,F|97,12,0,F|97,19,0,F|97,26,0,F|97,29,0,F|97,36,0,F|98,2,0,F|98,9,0,F|98,12,0,F|98,19,0,F|98,26,0,F|98,29,0,F|98,36,0,F|100,0,3,V|99,1,1,V|100,37,3,U|99,38,1,U|93,3,0,d|93,4,0,d|93,6,0,d|93,5,0,d|93,11,0,d|93,10,0,d|93,9,0,d|93,14,0,d|93,13,0,d|93,15,0,d|93,16,0,d|93,22,0,d|93,23,0,d|93,25,0,d|93,24,0,d|93,27,0,d|93,28,0,d|93,32,0,d|93,33,0,d|93,34,0,d|93,35,0,d|94,34,0,d|94,12,0,C|94,10,0,Q|2,18,0,@|2,19,0,@|2,20,0,@|2,17,0,D|1,17,0,D|0,16,0,U|1,16,0,K|3,17,0,@|3,17,0,T|4,16,0,D|4,15,0,D|5,14,3,V|4,17,0,@|3,16,0,D|2,16,0,D|3,15,3,V|3,18,0,@|3,19,0,@|3,19,3,e|4,19,0,@|4,20,0,@|4,20,0,E|4,21,0,@|4,21,2,e|3,21,0,@|3,22,0,D|2,22,0,D|2,23,1,U|4,23,0,D|5,23,0,D|5,22,0,@|6,21,3,f|6,22,0,@|4,22,0,D|5,21,0,@|5,20,0,@|5,19,0,@|5,18,0,@|5,18,0,E|6,18,0,@|6,17,3,g|7,17,0,@|7,17,0,D|8,17,0,@|8,17,2,B|8,16,0,@|8,16,1,h|8,15,0,@|7,16,0,@|7,16,0,D|6,15,0,D|6,16,0,@|7,18,0,@|7,18,0,D|7,18,3,A|7,19,0,@|7,19,1,C|8,19,0,@|8,20,0,@|8,21,0,@|8,21,0,B|8,22,0,@|8,23,1,h|8,23,0,@|9,22,0,@|9,22,0,Q|10,22,0,@|10,23,2,i|11,22,0,@|11,22,0,D|11,21,0,@|11,21,0,D|11,20,0,@|11,20,1,j|11,19,0,@|11,18,0,@|12,18,3,j|11,17,0,@|11,17,0,D|11,17,0,A|11,16,0,@|11,16,0,D|11,15,0,@|11,15,0,D|11,15,3,A|11,14,0,@|11,14,0,D|11,13,0,@|11,13,0,D|11,12,0,D|11,11,3,V|10,21,0,@|10,21,0,D|9,21,0,@|9,21,0,C|9,20,0,@|9,19,0,@|9,18,0,@|6,17,0,@|3,20,0,@|2,21,0,D|1,21,0,D|0,21,0,V|0,20,0,F|0,19,0,F|1,20,0,D|1,19,0,D|1,18,0,D|0,18,0,F|5,17,0,@|5,17,0,e|4,18,0,@|5,16,0,@|5,16,0,k|5,15,0,D|6,14,0,D|7,14,0,D|7,13,3,V|8,13,0,D|9,13,0,D|9,14,0,@|9,14,0,l|9,12,3,V|1,22,2,K|4,24,1,U|6,24,0,D|6,25,1,U|8,25,0,D|8,26,1,U|10,26,0,D|10,27,1,U|12,27,0,D|12,28,1,U|14,28,0,D|14,29,1,U|16,29,0,D|16,30,1,U|18,30,0,D|18,31,1,U|20,31,0,D|20,32,0,G|21,32,0,D|21,33,0,G|22,33,2,m|23,33,0,C|24,33,2,m|25,33,0,D|26,34,1,\|27,33,2,V|26,33,0,F|25,32,0,D|25,31,0,D|24,31,0,@|24,31,3,T|23,31,0,@|22,31,0,@|22,30,0,B|22,29,0,@|21,29,1,j|22,28,0,@|22,27,0,@|22,27,3,j|22,26,0,@|21,26,1,j|22,25,0,@|22,24,0,@|22,24,3,j|22,23,0,B|22,22,0,@|22,22,2,T|22,21,0,@|22,20,0,@|22,19,0,@|22,19,3,n|22,18,0,@|22,18,3,n|22,17,0,@|22,16,0,@|22,15,2,B|22,14,0,@|21,14,1,j|22,13,0,@|22,12,0,@|22,12,3,j|22,11,0,@|21,11,1,j|22,10,0,@|22,9,0,@|22,9,3,j|22,8,2,B|22,7,0,@|22,6,0,D|22,5,0,m|23,30,0,C|24,30,0,D|24,29,0,D|25,29,0,D|26,30,2,[|25,27,2,[|24,28,0,D|25,30,0,D|24,32,0,@|23,32,0,@|22,32,0,D|21,31,0,D|21,31,1,A|20,30,0,D|19,30,0,D|19,29,0,D|19,28,0,@|19,28,2,i|18,27,0,@|17,27,0,@|17,28,2,i|16,27,0,@|15,27,0,D|15,26,0,D|14,26,0,@|14,26,2,h|13,25,0,@|13,24,0,@|14,23,3,o|13,23,0,@|13,26,0,@|14,25,0,@|15,25,0,D|16,25,0,@|16,25,1,i|18,25,0,@|18,24,0,@|18,23,0,C|18,22,0,@|18,21,0,@|18,20,0,@|18,19,0,@|18,18,0,@|18,17,0,@|18,16,0,@|18,15,0,C|18,14,0,@|18,13,0,@|18,12,0,@|18,11,0,@|18,10,0,@|18,10,0,l|18,9,0,D|18,8,0,D|19,7,3,V|17,24,0,@|17,25,0,@|16,24,0,@|16,24,1,l|16,23,0,B|16,22,0,@|17,22,2,T|15,22,0,D|15,21,0,D|14,21,0,@|14,21,0,D|13,21,0,@|13,21,0,C|14,20,0,@|14,19,0,@|15,19,1,C|15,18,0,D|15,17,0,D|15,16,0,D|15,15,0,D|15,14,0,D|15,14,3,A|15,13,0,D|15,12,0,D|15,11,0,D|15,10,0,D|15,9,3,V|14,18,0,@|15,20,0,D|16,20,0,@|16,21,1,T|16,21,0,@|16,26,0,@|17,28,0,@|17,26,0,@|18,26,0,@|19,26,0,@|18,28,0,@|18,28,2,l|20,28,0,D|19,27,0,@|18,29,0,D|17,29,0,D|16,28,0,D|15,28,0,D|14,27,0,D|13,27,0,D|12,26,0,D|11,26,0,D|11,25,0,@|11,25,0,D|11,24,0,@|11,24,0,D|10,25,0,D|9,25,0,D|9,24,0,@|7,24,0,D|6,23,0,D|6,20,0,@|6,21,0,@|6,19,0,@|7,20,0,@|7,20,3,B|7,21,0,@|7,21,0,D|7,22,0,@|7,22,0,D|9,17,0,@|9,17,0,C|8,18,0,@|9,16,0,@|8,14,0,D|9,15,0,@|7,15,0,@|7,15,0,D|9,23,0,@|8,24,0,D|7,23,0,@|7,23,0,D|10,23,0,@|11,23,0,@|11,23,0,D|11,23,3,A|10,24,0,@|10,24,2,l|12,22,0,@|12,21,0,@|12,21,0,B|12,20,0,@|10,20,0,@|12,19,0,@|13,20,0,@|10,19,0,@|12,18,0,@|10,18,0,@|12,17,0,@|12,17,2,B|13,17,0,@|13,17,0,C|13,16,0,@|13,15,0,@|13,14,0,@|14,14,3,p|13,13,0,@|13,12,0,@|14,12,3,p|13,11,0,D|13,10,3,V|13,18,0,@|10,17,0,@|10,17,0,D|12,16,0,@|10,16,0,@|12,15,0,@|10,15,0,@|10,14,0,i|12,14,0,@|10,14,0,@|12,13,0,@|10,13,0,D|12,12,0,D|10,12,0,D|12,11,0,D|26,32,0,F|21,30,0,@|21,30,0,D|23,29,0,@|21,29,0,@|21,28,0,@|20,29,0,D|23,28,0,@|23,27,0,@|21,27,0,@|21,26,0,@|20,27,0,D|23,26,0,@|21,25,0,@|20,25,0,D|20,26,0,D|20,26,3,A|23,25,0,@|24,25,0,D|24,24,0,D|25,25,2,U|25,23,0,D|26,23,0,D|27,23,0,D|27,25,0,[|28,26,0,F|28,28,0,[|29,29,0,F|29,31,0,[|30,32,0,F|30,34,0,[|31,35,0,F|31,36,0,G|32,36,0,F|33,36,0,F|34,36,0,F|35,36,0,F|36,36,0,F|37,36,0,F|38,36,0,F|39,36,0,F|40,36,0,F|41,36,0,F|42,36,0,F|43,36,0,F|44,36,0,F|45,36,0,F|46,36,0,F|47,36,0,F|48,36,0,F|49,36,0,F|50,36,0,F|50,35,0,F|51,35,0,I|51,34,3,G|52,34,0,F|53,34,1,I|53,35,0,G|53,32,0,@|51,31,0,@|50,31,0,D|50,32,0,D|49,32,3,G|49,33,2,F|48,33,2,F|47,33,2,F|46,33,2,F|45,33,2,F|44,33,2,F|43,33,2,F|42,33,2,F|41,33,2,F|40,33,2,F|39,33,2,F|38,33,2,F|37,33,2,F|36,33,2,F|35,33,2,F|34,33,2,F|33,33,2,F|32,33,0,F|32,34,0,F|32,32,0,D|32,31,0,D|31,31,0,@|31,30,0,W|31,29,0,@|32,29,0,D|33,29,0,D|34,29,1,D|34,30,1,D|35,30,1,D|36,30,0,@|36,29,0,@|36,28,0,@|36,27,0,@|36,26,0,@|36,25,1,F|35,29,0,@|34,28,1,C|33,27,0,D|33,27,0,A|32,27,0,D|32,27,3,A|32,26,0,D|32,25,3,B|32,24,0,D|32,23,0,D|32,22,0,D|32,21,0,D|32,20,0,D|32,20,3,H|32,19,1,C|32,18,1,B|32,17,0,D|32,16,0,D|32,15,0,D|32,14,0,D|32,13,3,B|32,12,0,D|32,11,0,D|32,11,3,A|32,10,1,C|32,9,0,D|32,8,0,D|32,7,0,D|32,6,0,D|32,5,0,F|32,4,0,F|32,3,0,F|32,2,0,F|34,26,1,D|34,25,3,G|33,28,0,@|32,28,1,C|31,28,0,@|30,28,0,@|30,27,0,W|30,26,0,N|30,26,0,@|30,25,0,@|29,24,0,Y|30,23,0,D|30,22,0,@|28,22,1,^|30,21,0,@|30,20,0,@|28,20,1,^|30,19,0,@|30,18,0,@|28,18,1,^|30,17,0,@|30,16,0,@|28,16,1,^|30,15,0,D|30,14,0,@|29,13,0,Y|30,13,0,@|29,23,0,D|29,23,2,M|29,24,0,@|29,25,0,@|30,24,0,@|30,27,0,@|31,30,0,@|32,30,0,D|33,34,0,I|33,32,1,I|37,34,0,G|38,34,2,F|39,34,0,I|43,34,0,G|44,34,2,F|45,34,0,I|49,34,0,G|50,30,0,D|50,29,0,D|48,29,1,F|47,29,0,@|46,29,0,@|45,29,0,@|44,29,0,@|43,29,0,@|42,29,0,@|41,29,0,@|40,29,0,@|39,29,0,@|38,29,0,@|38,30,0,@|38,31,1,D|38,31,2,A|37,31,1,D|39,31,1,D|40,31,1,D|41,31,1,D|42,31,1,D|43,31,1,D|44,31,1,D|44,31,2,A|45,31,1,D|46,31,1,D|47,31,1,D|48,31,1,G|38,28,0,@|38,27,0,@|39,27,0,@|40,27,0,@|41,27,0,@|42,27,0,@|43,27,0,@|44,27,0,@|45,27,0,@|46,27,0,@|47,27,0,@|48,27,1,F|50,27,0,D|50,27,1,A|51,27,0,@|51,28,0,@|52,28,0,@|52,29,0,@|53,29,0,@|53,28,0,@|53,27,0,@|53,26,0,@|52,24,0,@|52,25,0,@|52,26,0,@|53,25,0,@|52,27,0,@|51,26,0,@|50,26,0,D|50,25,1,B|50,24,0,D|49,24,3,I|49,23,0,D|48,23,0,D|47,23,0,D|46,23,0,D|45,23,0,D|45,22,0,@|45,21,0,@|46,22,0,@|47,22,0,@|49,21,0,@|50,21,0,D|50,19,1,C|50,18,0,D|50,18,1,A|50,17,0,D|50,16,0,D|50,15,0,D|50,14,0,D|50,13,1,B|50,12,0,D|50,11,0,D|50,11,1,A|50,10,1,C|50,9,0,D|50,8,0,D|50,7,0,D|50,6,0,D|50,4,0,F|50,3,0,F|50,2,0,F|49,20,0,@|48,20,0,@|48,19,0,@|47,19,0,@|46,19,0,@|46,18,0,@|46,16,0,@|47,18,0,@|48,18,0,@|48,17,0,@|48,15,0,D|47,15,0,D|48,16,0,@|47,20,0,@|48,21,0,@|48,22,0,@|49,22,0,@|50,23,0,D|48,26,1,F|48,25,1,I|47,25,1,F|46,25,1,F|45,25,1,F|44,25,1,F|43,25,1,F|42,25,1,F|41,25,1,F|40,25,1,F|39,25,1,F|38,25,1,F|47,26,1,F|46,26,0,@|45,26,0,@|44,26,0,@|43,26,0,@|42,26,0,@|41,26,0,@|40,26,0,O|40,26,0,@|39,26,0,@|38,26,0,@|39,30,0,@|39,28,0,@|40,30,0,@|40,28,0,@|41,30,0,@|41,28,0,@|42,30,0,@|42,28,0,@|43,30,0,@|43,28,0,@|44,30,0,@|44,28,0,@|45,30,0,@|45,28,0,@|46,30,0,@|46,28,0,@|47,30,1,F|47,28,0,@|48,30,1,F|48,28,1,F|51,29,0,@|50,28,1,C|51,30,0,@|51,32,0,@|53,30,0,@|52,30,0,@|52,31,0,@|52,32,0,@|53,31,0,@|50,34,0,F|49,35,2,I|45,35,2,G|44,35,2,F|43,35,2,I|39,35,2,G|38,35,2,F|37,35,2,I|33,35,2,G|32,35,0,F|31,34,0,F|31,33,0,F|31,32,0,F|30,31,0,F|30,30,0,F|30,29,0,F|29,28,0,F|29,27,0,F|29,26,0,F|28,25,0,D|28,24,0,D|28,23,0,D|27,22,0,@|26,22,0,D|26,21,0,D|25,21,0,@|25,21,1,q|24,20,0,@|24,19,0,@|24,18,0,@|25,18,0,@|25,17,0,@|25,16,3,T|24,16,0,@|24,15,0,D|24,14,0,D|25,14,2,V|25,11,2,\|24,10,0,D|24,9,0,D|24,8,0,D|25,8,0,D|26,8,2,\|26,6,0,F|25,6,0,D|24,6,0,@|24,6,3,T|24,5,0,m|25,5,0,D|26,4,3,[|27,6,2,U|26,5,0,F|25,7,0,D|24,7,0,@|24,11,0,D|24,12,0,D|24,12,3,A|25,9,0,D|24,13,0,D|25,15,0,D|26,15,0,D|26,17,0,D|25,16,0,@|24,17,0,@|24,22,0,@|25,19,0,@|26,19,1,C|24,21,0,@|25,20,0,@|25,22,0,@|24,23,0,D|23,24,0,@|21,24,0,@|21,23,0,D|21,23,2,A|20,23,0,D|20,24,0,D|23,23,0,C|23,22,0,@|21,22,0,@|21,21,0,@|20,21,0,@|20,20,0,@|20,19,0,@|20,18,0,r|20,17,0,@|20,17,0,n|20,16,0,@|20,16,0,Q|20,15,0,D|20,18,0,@|20,22,0,@|20,22,2,s|23,21,0,@|23,20,0,@|21,20,0,@|21,20,0,E|23,19,0,@|21,19,0,@|23,18,0,@|21,18,0,@|23,17,0,@|21,17,0,@|21,17,0,n|23,16,0,@|21,16,0,@|23,15,0,C|21,15,0,D|21,15,0,A|23,14,0,@|21,14,0,@|21,13,0,@|20,13,0,D|20,14,0,D|23,13,0,@|23,12,0,@|21,12,0,@|21,11,0,@|20,12,0,D|20,12,3,A|23,11,0,@|21,10,0,@|20,10,0,D|20,11,0,D|23,10,0,@|23,9,0,@|21,9,0,@|21,8,0,D|20,8,0,D|20,9,0,D|23,8,0,C|23,7,0,@|21,7,0,D|21,7,1,A|23,6,0,@|21,6,0,D|20,6,2,I|23,5,0,C|21,5,2,I|24,27,0,D|24,26,0,D|24,26,3,A|12,25,0,@|14,24,0,@|12,24,0,@|14,23,0,@|13,22,0,@|14,22,0,@|14,22,3,l|15,23,0,D|15,24,0,D|15,24,3,A|12,23,0,@|19,25,0,@|19,24,3,h|19,24,0,@|19,23,0,D|17,23,0,D|19,22,0,@|17,22,0,@|19,21,0,@|17,21,0,@|19,20,0,@|17,20,0,@|19,19,0,@|19,19,1,n|17,19,0,@|19,18,0,@|19,18,1,n|17,18,0,@|19,17,0,@|17,17,0,@|19,16,0,@|17,16,0,@|19,15,0,D|17,15,0,D|19,14,0,@|19,13,3,h|17,14,0,@|16,14,1,i|19,13,0,@|17,13,0,@|19,12,0,@|17,12,0,@|16,12,1,i|19,11,0,@|19,10,0,i|17,11,0,@|19,10,0,@|17,10,0,@|19,9,0,D|17,9,0,D|19,8,0,D|17,8,3,V|20,7,0,D|13,19,0,@|16,19,0,@|16,18,0,@|16,18,2,n|16,17,0,@|16,17,0,t|14,17,0,@|14,17,0,D|16,16,0,@|16,16,0,n|14,16,0,@|14,15,3,T|16,15,2,B|14,15,0,@|16,14,0,@|14,14,0,@|16,13,0,@|16,13,1,l|14,13,0,@|14,13,1,u|16,12,0,@|14,12,0,@|16,11,0,@|16,11,1,l|14,11,0,D|16,10,0,D|14,10,0,D|16,9,0,D|34,31,3,I|35,31,1,D|37,30,0,@|36,31,1,D|37,29,0,@|37,28,0,@|35,28,0,@|37,27,0,@|35,27,0,@|37,26,0,@|35,26,1,F|37,25,1,F|35,25,1,F|31,27,0,@|31,26,0,@|31,25,0,@|33,24,1,G|31,24,0,@|33,23,0,D|34,23,0,D|35,23,0,D|36,23,0,D|36,23,2,A|37,23,0,D|38,23,0,D|39,23,0,D|40,23,0,D|41,23,0,D|42,23,0,D|43,23,0,D|43,22,0,@|43,21,0,@|42,21,0,@|41,21,0,T|40,21,0,@|39,21,0,@|38,21,0,@|39,19,0,O|39,19,0,@|40,19,0,@|41,19,0,v|43,19,0,@|44,19,0,@|44,20,0,@|44,18,0,@|43,18,0,@|43,17,0,@|43,16,0,@|42,16,0,@|41,16,0,N|41,16,0,@|40,16,0,@|39,16,0,@|39,15,0,D|38,15,0,D|37,15,0,D|36,15,0,D|36,15,0,A|35,15,0,D|34,15,0,D|40,15,0,D|41,15,0,D|42,15,0,D|43,15,0,D|44,15,0,D|42,17,0,R|42,17,0,@|41,17,0,N|41,17,0,@|41,17,2,T|40,17,0,@|42,19,0,@|42,18,0,@|41,18,0,@|41,19,0,@|40,18,0,@|39,18,0,@|39,17,0,@|38,16,0,@|37,16,0,@|36,16,0,@|35,16,0,@|34,16,0,@|38,19,0,@|38,18,0,@|38,17,0,@|37,18,0,@|37,17,0,@|36,21,0,@|36,18,0,@|36,17,0,@|35,21,0,@|35,19,0,@|35,17,0,@|34,21,0,@|34,20,0,@|34,19,0,@|34,18,0,@|34,17,0,@|37,21,0,@|38,20,0,@|39,20,0,@|40,20,0,@|41,20,0,@|41,21,0,P|41,21,0,@|42,20,0,@|43,20,0,@|42,22,0,@|41,22,0,P|41,22,0,@|40,22,0,@|39,22,0,@|38,22,0,@|37,22,0,@|36,22,0,Q|36,22,0,@|35,22,0,@|34,22,0,@|31,23,0,C|33,22,0,@|31,22,0,@|33,21,0,@|31,21,0,@|33,20,0,@|31,20,0,@|33,19,0,@|31,19,0,@|33,18,0,@|31,18,0,@|33,17,0,@|31,17,0,@|33,16,0,@|31,16,0,@|33,15,0,D|31,15,0,C|33,14,1,I|31,14,0,@|31,13,0,@|31,12,0,Q|31,12,0,@|33,11,0,D|33,11,2,A|34,11,1,D|34,12,1,D|34,13,3,I|35,13,1,D|36,13,1,D|37,13,1,D|38,13,1,D|38,13,2,A|39,13,1,D|40,13,1,D|41,13,1,D|42,13,1,D|43,13,1,D|44,13,1,D|44,13,2,A|45,13,1,D|46,13,1,D|47,13,1,D|48,13,1,G|48,12,1,F|48,11,1,F|47,11,0,@|46,11,0,@|45,11,0,@|44,11,0,@|43,11,0,@|42,11,0,@|41,11,0,@|40,11,0,@|39,11,0,@|38,11,0,@|37,11,0,@|36,11,0,@|36,10,0,@|35,10,0,@|35,9,0,@|34,8,1,D|34,7,3,G|35,7,1,F|36,7,1,F|36,8,0,@|37,8,0,@|37,9,0,@|38,9,0,@|39,9,0,@|40,9,0,@|41,9,0,@|42,9,0,@|43,9,0,@|44,9,0,@|45,9,0,@|46,9,0,@|47,9,0,@|48,9,1,F|48,8,1,F|48,7,1,I|47,7,1,F|46,7,1,F|45,7,1,F|44,7,1,F|43,7,1,F|42,7,1,F|41,7,1,F|40,7,1,F|39,7,1,F|38,7,1,F|47,8,1,F|46,8,0,@|45,8,0,@|44,8,0,@|43,8,0,@|42,8,0,@|41,8,0,@|40,8,0,O|40,8,0,@|39,8,0,@|38,8,0,@|37,7,1,F|35,8,1,F|36,9,0,@|37,10,0,@|38,10,0,@|39,10,0,@|40,10,0,@|41,10,0,@|42,10,0,@|43,10,0,@|44,10,0,@|45,10,0,@|46,10,0,@|47,10,0,@|48,10,1,F|47,12,1,F|46,12,0,@|45,12,0,@|44,12,0,@|43,12,0,@|42,12,0,@|41,12,0,@|40,12,0,@|39,12,0,@|38,12,0,@|37,12,0,@|36,12,0,@|35,12,1,D|35,11,0,@|34,10,1,C|31,11,0,@|30,11,0,@|30,10,0,W|29,10,0,F|28,10,0,\|28,12,0,F|27,13,0,\|29,9,0,F|29,7,0,\|30,8,0,F|30,7,0,F|30,6,0,F|30,4,0,\|30,9,0,F|29,11,0,F|30,10,0,@|33,10,0,@|31,10,0,@|33,9,0,D|31,9,0,@|31,8,0,@|31,7,0,W|31,7,0,@|33,6,1,G|31,6,0,F|33,5,0,F|34,5,0,F|35,5,0,F|36,5,0,F|37,5,0,F|38,5,0,F|39,5,0,F|40,5,0,F|41,5,0,F|42,5,0,F|43,5,0,F|44,5,0,F|45,5,0,F|46,5,0,F|47,5,0,F|48,5,0,F|45,4,2,G|45,3,0,I|44,3,0,F|43,3,0,G|43,2,0,F|42,2,0,F|41,2,0,F|40,2,0,F|39,2,0,F|38,2,0,F|37,2,0,F|36,2,0,F|35,2,0,F|34,2,0,F|37,3,0,G|38,3,0,F|39,3,0,I|44,2,0,F|45,2,0,F|46,2,0,F|47,2,0,F|48,2,0,F|44,4,0,F|43,4,2,I|39,4,2,G|38,4,0,F|37,4,2,I|31,5,0,F|33,4,2,G|31,4,0,F|33,3,0,I|31,3,0,F|33,2,0,F|31,2,2,I|29,22,0,@|28,22,0,@|27,21,0,@|28,21,0,@|29,21,0,@|29,21,0,E|29,20,0,@|27,20,0,@|28,20,0,@|27,19,0,@|28,19,0,@|29,19,0,@|26,20,1,B|29,18,0,@|27,18,0,@|28,18,0,@|27,17,0,@|28,17,0,@|29,17,0,@|26,18,3,B|29,16,0,@|27,16,0,@|28,16,0,@|27,15,0,D|28,15,0,D|29,15,0,D|29,15,0,M|26,16,0,D|29,14,0,@|29,13,0,@|29,12,0,F|30,12,0,N|30,12,0,@|28,14,0,D|28,13,0,D|53,24,0,@|51,25,0,@|51,24,0,@|52,22,0,@|53,20,0,@|53,19,0,@|52,19,0,@|52,18,0,@|52,17,0,@|53,13,0,@|53,11,0,@|53,10,0,@|52,10,0,@|52,9,0,@|53,7,0,@|53,4,1,G|52,4,0,F|53,3,2,I|52,6,0,@|53,6,0,@|52,7,0,@|53,8,0,@|52,8,0,@|53,9,0,@|52,11,0,@|52,12,0,@|53,12,0,@|52,13,0,@|52,14,0,@|53,14,0,@|53,16,0,@|53,17,0,@|52,16,0,@|53,18,0,@|52,20,0,@|53,21,0,@|51,22,0,@|52,21,0,@|53,22,0,@|44,23,0,D|44,22,0,@|45,20,0,@|46,20,0,@|47,21,0,@|44,21,0,@|51,21,0,@|50,22,0,D|51,20,0,@|51,19,0,@|49,19,0,@|51,18,0,@|49,18,0,@|51,17,0,@|49,17,0,@|51,16,0,@|49,16,0,@|49,15,0,D|51,14,0,@|49,14,3,G|51,13,0,@|51,12,0,@|51,11,0,@|51,10,0,@|51,9,0,@|51,8,0,@|51,7,0,@|51,6,0,@|49,6,3,I|49,5,0,F|51,4,3,I|49,4,2,I|51,3,2,G|49,3,0,G|49,2,0,F|45,19,0,@|45,18,0,@|47,17,0,@|45,17,0,@|45,16,0,@|45,15,0,D|46,15,0,D|47,16,0,@|44,17,0,@|44,16,0,@|3,17,0,w|24,31,0,x|22,22,0,y|16,22,0,z|17,22,0,z|16,20,0,{|16,21,0,z|25,17,0,}|25,16,0,~|24,6,0,x|24,7,0,|21,22,0,y|21,19,0,{|14,16,0,|36,9,0,S|36,27,0,S|41,17,0,|62,17,0,|64,21,0,|41,21,0,|63,17,0,|81,21,3,T|79,22,1,T|81,15,2,|81,23,0,H|90,4,0,X|88,4,0,X|86,4,0,X|86,33,0,X|88,33,0,X|90,33,0,X|85,31,0,|88,31,0,|88,6,0,|85,6,0,|38,6,0,F|44,6,0,F|49,9,0,F|49,11,0,F|38,14,0,F|44,14,0,F|44,24,0,F|38,24,0,F|38,32,0,F|44,32,0,F|60,32,0,F|66,32,0,F|66,24,0,F|60,24,0,F|49,27,0,F|49,29,0,F|71,29,0,F|71,27,0,F|71,11,0,F|71,9,0,F|66,6,0,F|60,6,0,F|60,14,0,F|66,14,0,F|52,31,0,|52,7,0,|35,18,0,@|35,20,0,@|36,19,0,@|36,20,0,@|37,19,0,@|37,20,0,@|46,17,0,@|46,21,0,@|57,17,0,@|57,21,0,@|58,17,0,@|59,21,0,@|68,19,0,@|36,19,0,|46,19,0,|45,20,0,|46,20,0,|47,19,0,|46,18,0,|45,19,0,|47,20,0,|52,15,0,D|53,15,0,D|52,23,0,D|53,23,0,D|50,33,0,F|51,33,0,F|52,33,0,F|53,33,0,F|54,33,0,F|50,5,0,F|51,5,0,F|52,5,0,F|53,5,0,F|54,5,0,F|51,15,0,C|51,23,0,C|52,24,0,X|52,26,0,X|52,13,0,X|52,11,0,X|52,16,0,|52,21,0,|50,20,1,B|58,23,2,A|58,15,0,A|46,15,0,A|46,23,2,A|34,9,1,B|56,9,1,B|56,27,1,B|34,27,1,B|52,9,1,W|52,29,1,W|71,22,2,T|55,16,0,T|70,16,0,T|56,22,2,T|56,17,0,|66,17,0,|13,12,0,|14,12,0,|12,13,0,|13,13,0,|14,13,0,|12,14,0,|13,14,0,|14,14,0,|12,15,0,|13,15,0,|14,15,0,|12,16,0,|13,16,0,|14,16,0,</bigString>
	</EnemyShipDef>
</Defs>